Workbook

Sheet 사용법
A1: 기본 사용법
B2: 1. 반드시 인터넷 익스플로러(크롬 안됨)를 이용해서, comp.fnguide.com(www.fnguide.com 아님)에 접속합니다.
B3: 2. 우상단 창에 원하는 종목을 입력하여 검색하신 후, snapshot 화면을 전체선택(ctrl + a)하고 복사하여(ctrl + c) "FN_Snapshot" 시트의 A1셀을 선택한 다음 '주변서식에 맞추기'로 붙여 넣습니다.
B4: 3. 결과 시트를 확인합니다.
A6: 크롬(Chrome) 사용법
B7: 1. 인터넷 익스플로러 서비스가 중단됨에 따라, 구글 크롬(Chrome)에서도 본 마법사를 활용하는 방법을 안내드립니다.
B8: 2. 크롬에서 chrome 웹 스토어(https://chrome.google.com/webstore/category/extensions?hl=ko)로 접속합니다.
B9: 3. 좌측 상단 '스토어 검색'에서 'IE Tab' (대소문자 관계 없음)을 검색합니다.
B25: 4. 첫번째로 나오는 IE Tab을 클릭하고, 우측에 있는 'Chrome에 추가' 버튼을 클릭하고, '확장 프로그램 추가'를 클릭합니다.
B39: 5. 즉시 추가가 되고, 우측 상단에 퍼즐모양 아이콘을 클릭하고 IE Tab을 클릭합니다.
B52: 6. 이제 IE Tab을 통해서 comp.fnguide.com으로 접속하고, 위의 '기본 사용법'을 따라 동일하게 진행합니다.
A56: RIM 수기계산 사용
B57: 여러 가지 에러 상황(정확한 원인은 알 수 없으나, 붙여넣기만 하면 엑셀이 그냥 다운되버린다는 경우 등이 간혹 있음)에 대비하여, 수기계산 시트 추가
B58: "[Type 1] 단순입력(간편식-책)"은 책 "재무제표 모르면 주식투자 절대로 하지 마라"에 소개된 계산식을 바탕으로 주황색 시트에 기초자료 입력하여 산출
B59: "[Type 2] 단순입력(성장반영 10년 시뮬레이션)"은 Type 1이 성장을 반영하지 못한다는(초과이익이 단순히 계속된다는 가정) 단점을 고려하여, 회사가 ROE를 유지하면 이익은 계속 증가한다는 점을 시뮬레이션을 통해 반영
B60: "[Type 3] 상세입력(성장반영 10년 시뮬레이션)"은 fnguide 화면 조회는 되나 붙여넣기가 안되는 경우(붙여넣기만 하면 컴퓨터가 다운되거나 먹통이 되는 등 개개인의 PC사정에 따라 다양한 경우가 있음)를 대비하여 주황색 란에 직접 fnguide 자료를 입력하여 산출
A62: 연도 오류 발생시 대처법
B63: Snapshot에 붙여넣을 때 연도 데이터는 날짜 형식으로 붙고, 일반숫자는 숫자 형식으로 붙게 되는데 새로 붙여 넣은 회사의 연도 위치가 다르면 주변서식에 맞추기를 선택했을 때 날짜가 일반 숫자 형식으로 인식되어 오류가 발생함
B64: 해결 방법은 기존에 인식된 서식을 지우는 것임
B65: FN_Snapshot의 A부터 I까지의 열을 선택한 다음 홈 메뉴의 지우기 - '모두 지우기' 나 '서식 지우기'를 선택하면 됨
B66: 이렇게 서식을 지운 다음 다시 '주변서식에 맞추기'로 붙여 넣으면 됩니다.
A76: 업데이트 내용
B77: (V30)
B78: Snapshot만 붙여 넣어도 되도록 변경(재무제표와 컨센서스를 붙여 넣을 필요가 없습니다)
B79: 달라진 fnguide 양식 반영
B80: RIM수기계산 시트 추가
B81: 업종비교 추가
B83: (V31)
B84: 연도 오류 발생시 대처법 추가
B86: (V32)
B87: 일부 신규상장 종목에 대한 오류 개선
B89: (V33)
B90: 컨센서스 이용시 컨센 3년 + 10년으로 총 13년의 초과이익을 가져오던 것을, 다른 방법과 동일하게 3년+7년으로 10년을 가져와 계산하도록 변경
A92: 참고영상
B93: 실적이 좋아져도 주가가 빠지는 이유 5분 정리 [헬프미 사프로 Ep.01]
B94: 영업이익은 마이너스, 그런데 현금흐름은 플러스? 이런 회사 괜찮을까? [헬프미 사프로 Ep.02]
B95: ROE가 큰 순환주기를 그리는 산업군, 평균값 어떻게 정하죠? [헬프미 사프로 Ep.03]
B96: 자산이라고 다 같은 자산이 아니다? [헬프미 사프로 Ep.04]
B97: 유상증자를 할 때 재무제표에서 살펴볼 것은? [헬프미 사프로 Ep.05]
B98: 복잡한 이벤트가 잦은 회사, 과연 투자해도 괜찮을까? [헬프미 사프로 Ep.06]

Sheet FN_Snapshot
A1: 본문 바로가기 메뉴 바로가기
A3: 상장기업분석
A5: 리포트 조회 통합 모바일앱 리타민 출시리포트 조회 통합 모바일앱 리타민 출시
A6: 열기
A7: 인쇄
A9: 기업정보
A10: Snapshot기업개요재무제표재무비율투자지표컨센서스
A11: 지분분석업종분석경쟁사비교거래소공시금감원공시
A12: ETF/ETN 정보
A13: ETF Snapshot 성과 및 위험분석 ETN Snapshot
A14: 리포트
A15: 리포트동향 요약리포트
... A26: 세방
A28: 5930
A30: | 홈페이지
A32: 홈페이지
A33: http://www.samsung.com
A35: 전화번호
A37: 전화번호
A38: 031-200-1114 | IR 담당자 02-2255-9000
A40: 주소
A42: 주소
A43: 경기도 수원시 영통구 삼성로 129 (매탄동)
A45: KSE 코스피 전기,전자코스피 전기,전자 |FICS 휴대폰 및 관련부품|12월 결산|K200
A47: PER(Price Earning Ratio)
A48: 전일자 보통주 수정주가 / 최근 결산 EPS(주당순이익)
... A51: PER
A52: 3
A54: 12M PER
A55: 전일자 보통주 수정주가 / 12개월 Forward EPS
A56: 12M PER
A57: 10.55
A59: 업종 PER
A60: 시장대표업종||SUM(구성종목 시가총액)/SUM(구성종목 당기순이익)
A61: * 전일자 보통주 시가총액 기준
A62: * 당기순이익은 최근결산 2021/12 (연간) 기준임.
A63: 업종 PER
A64: 6.31
A66: PBR(Price Book-value Ratio)
A67: 전일자 보통주 수정주가 / 최근 결산기 BPS(주당순자산)
A68: * BPS=(지배주주지분-자기주식) / 무상조정기말주식수(우선주 및 자사주 포함)
A69: * 최근결산은 2021/12 (연간) 기준임.
A70: PBR
A71: 0.22
A73: 배당수익률
A74: {최근 결산기 보통주 DPS(현금, 무상조정) / 전일자 보통주 수정주가} *100
A75: * 최근결산은 2021/12 (연간) 기준임.
A76: 배당수익률
A77: 0.0269
A79: 3개월1년3년
A81: SELLBUY
A83: 외국인 보유비중 시가총액
A85: 삼성전자 코스피 전기,전자 KOSPI
A87: 주가추이, 내부자거래1년
A89: 71700
A90: 주가추이,내부자거래 차트: 자세한 내용은 클릭후 팝업창 참고
A92: 외국인 보유비중, 시가총액1년
A94: 52.1
A95: 외국인 보유비중,시가총액 차트 : 자세한 내용은 클릭후 팝업창 참고
A98: 상대수익률
A99: * 상대수익률은 조회시작일의 값을 100포인트로 변환하여 산출된
A100: 값입니다.
A101: * 특정일의 상대수익률 포인트는 (특정일의 지수 및 주가/조회 기준
A102: 시작점의 지수 및 주가) * 100 입니다.
A104: 상대수익률1년
A106: -14.23
A107: 상대수익률 차트 : 자세한 내용은 클릭후 팝업창 참고
A109: 시세현황
A111: [2022/03/02]
A112: 단위 : 원, 주,%
A113: 시세현황
A114: 종가/ 전일대비 | B114: 15,770/ | C114: 거래량 | D114: 12481430
A115: 52주.최고가/ 최저가 | B115: 86,000/ 68,800 | C115: 거래대금(억원) | D115: 8974
A116: 수익률(1M/ 3M/ 6M/ 1Y) | B116: =-2.18/ -5.41/ -5.66/ -14.23 -> 0.0050030852 | C116: 외국인 보유비중 | D116: 52.1
A117: 시가총액(상장예정포함) | B117: 4819325 | C117: 베타(1년) | D117: 0.54398
A118: 시가총액(상장예정포함): 종가*(상장주식수+상장예정주식수), (보통주+우선주)
A119: 시가총액(보통주)+시가총액(우선주)
A120: * 상장예정주식수: 유무상증자, 주식배당의 권리락일(배당락일)이 지났으나, 상장되지 않은 주식수
A122: 시가총액(상장예정포함,억원)
A123: 시가총액(보통주) | B123: 4280334 | C123: 액면가 | D123: 100
A124: 종가(보통주)*상장주식수(보통주)
A126: 시가총액(보통주,억원)
A128: 발행주식수(보통주/ 우선주) | B128: 19,115,603/ 3,689,250 | C128: 유동주식수/비율 | D128: 4,461,067,468 / 74.73
C129: 유동주식비율 = 유동주식수 / 지수산정주식수 * 100.
C130: 유동주식수 = 지수산정주식수-(최대주주등(본인+특별관계자)+우리사주+자사주+보호예수+정부기관(5%이상)+해외DR).
C132: 유동주식수/비율(보통주)
A134: 실적이슈
A136: [2021/12 기준, 결산]
A137: 실적이슈
A138: 확정실적(영업이익, 억원) | B138: 예상실적(영업이익, 억원) | C138: 3개월전예상실적대비(%) | D138: 전년동기대비(%)
A139: 516339 | C139: 306.18 | D139: 43.45
A141: 운용사별 보유 현황
A143: [2021/12]
A144: 단위 : 천주, 억원, %
A145: 운용사별 보유 현황
A146: 운용사명 | B146: 보유수량 | C146: 시가평가액 | D146: 상장주식수내비중 | E146: 운용사내비중
A147: 삼성자산운용 | B147: 52860.68 | C147: 41389.91 | D147: 0.89 | E147: 8.04
A148: 미래에셋자산운용 | B148: 34984.66 | C148: 27392.99 | D148: 0.59 | E148: 5.23
A149: 케이비자산운용 | B149: 11251.8 | C149: 8810.16 | D149: 0.19 | E149: 3.79
A150: 한국투자신탁운용 | B150: 11066.78 | C150: 8665.29 | D150: 0.19 | E150: 4.7
...

Sheet 결과
B1: 공인회계사 사경인 | E1: 사경인 실전투자 아카데미
B3: 기초자료
B4: 회사명 | C4: =Data!B4 -> 세방 | D4: 보통주발행주수 | E4: =Data!B7 -> 19115603
B5: 현재주가 | C5: =Data!B5 -> 15770 | D5: 우선주발행주수 | E5: =Data!C7 -> 3689250
B6: 베타(β) | C6: =Data!B6 -> 0.54398 | D6: 자기주식 | E6: =Data!B8 -> 784733 | AD6: 적용 | AE6: 1순위 | AF6: =G24 -> 0.044408524 | AH6: 초과이익 가정
AD7: 미적용 | AE7: 컨센서스 | AF7: =E24 -> 컨센 없음 | AH7: 할인(할증)률
B8: Business Summary | AE8: 가중평균 | AF8: =F24 -> 0.080183333
B9: =Data!A11 -> 반도체 호조로 사상 최대 분기 실적 | AE9: 최근 | AF9: =H22 -> 0.044408524
B10: =Data!A12 -> 한국 및 CE, IM부문 해외 9개 지역총괄과 DS부문 해외 5개 지역총괄, Harman 등 234개의 종속기업으로 구성된 글로벌 전자기업임. 세트사업에는 TV, 냉장고 등을 생산하는 CE부문과 스마트폰, 네트워크시스템, 컴퓨터 등을 생산하는 IM부문이 있음. 부품사업(DS부문)에서는 D램, 낸드 플래쉬, 모바일AP 등의 제품을 생산하는 반도체 사업과 TFT-LCD 및 OLED 디스플레이 패널을 생산하는 DP사업으로 구성됨. | AE10: 별도값 | AF10: =H24 -> 0.13
B11: =Data!A13 -> 메모리시장이 호황인 가운데 폴더블폰과 OLED 판매가 늘어나 3분기 매출액은 70조를 넘어서며 사상 최대의 실적을 달성함. 첨단공정 확대와 환율 영향으로 영업이익률도 20%를 넘어섬. 4분기 메모리시장은 당초 예상 대비 부품 수급 이슈 장기화에 따른 수요 리스크 확대가 우려됨. 북미 서버업체들의 반도체 재고가 3분기 대비 30% 이상 축소되며 반도체 재고 소진 속도가 예상을 상회하여 반도체 가격 반등 시점이 앞당겨질 전망임.
B13: 요구수익률
B14: 별도 요구수익률 | C14: 적용 | D14: 0.1026
B15: 무위험이자율 | C15: 0.0152
B16: 시장위험프리미엄 | C16: 0.0657
B17: 최종 적용 할인율 | C17: =IF(C14="적용",D14,C15+C16*C6) -> 0.1026
B18: 참고링크 | C18: 채권수익률
B20: ROE 추정 | C20: 가중평균 | D20: =VLOOKUP(C20,AE6:AF10,2,FALSE) -> 0.080183333 | E20: =IF(I20="연도오류","연도 오류 - 모두 지우기 실행하세요(사용법 시트 참조)","") | I20: =IF(Data!B26<2000,"연도오류","")
B21: 년도 | C21: =Data!B25 -> 44166 | D21: =Data!C25 -> 44531 | E21: =Data!D25 -> 44896 | F21: =Data!E25 -> 45261 | G21: =Data!F25 -> 45627 | H21: ="최근 4분기("&TEXT(Data!F50,"yy/mm")&")" -> 최근 4분기(25/12) | I21: =IF(H22="분기자료부족",IF(F22>E22,IF(G22>F22,"상승추세",""),""),IF(F22>E22,IF(H22>F22,"상승추세",""),"")) | J21: =Data!K50 -> 12 | K21: =MONTH(G21) -> 12 | L21: =MOD(J21+12-K21,12)/6 -> 0 | M21: =L21+4 -> 4 | N21: =MOD(J21+12-K21,12) -> 0
B22: ROE | C22: =Data!B40 -> 0.0389 | D22: =Data!C40 -> 0.0601 | E22: =Data!D40 -> 0.1112 | F22: =Data!E40 -> 0.0678 | G22: =Data!F40 -> 0.0781 | H22: =Data!K78 -> 0.044408524 | I22: =IF(H22="분기자료부족",IF(F22<E22,IF(G22<F22,"하락추세",""),""),IF(F22<E22,IF(H22<F22,"하락추세",""),"")) -> 하락추세 | J22: =IF(H22="분기자료부족",IF(I21="상승추세",G22,IF(I22="하락추세",G22,F24)),"")
B23: 컨센서스 | C23: =DATE(Data!G26,12,31) -> 46022 | D23: =DATE(Data!H26,12,31) -> 46387 | E23: =DATE(Data!I26,12,31) -> 46752 | F23: 가중평균 | G23: 1순위 | H23: 별도값
B24: ROE | C24: =IF(Data!G40="","컨센 없음",Data!G40) -> 컨센 없음 | D24: =IF(Data!H40="","컨센 없음",Data!H40) -> 컨센 없음 | E24: =IF(Data!I40="","컨센 없음",Data!I40) -> 컨센 없음 | F24: =IF(H22="분기자료부족",(G22*3+F22*2+E22)/6,IF(N21=0,(G22*3+F22*2+E22)/6,(H22*3+G22*L21+F22)/M21)) -> 0.080183333 | G24: =IF(E24="컨센 없음",IF(D24="컨센 없음",IF(C24="컨센 없음",IF(H22="분기자료부족",J22,IF(I21="상승추세",H22,IF(I22="하락추세",H22,F24))),C24),D24),E24) -> 0.044408524 | H24: 0.13
B26: RIM 적정주가 | C26: 초과이익 가정 | D26: 0.2
B27: 현재주가 | C27: =C5 -> 15770 | D27: 적정가 대비 | E27: 주당 가치 | F27: 주가 | G27: PER
B28: 적정주가 | C28: =IF(F31="정배열",F29,F28) -> 49792.041 | D28: =C27/C28-1 -> -0.68328272 | E28: 초과이익 지속 | F28: =RIM계산!C11 -> 49792.041 | G28: =RIM계산!E11 -> 12.823704
B29: 매도가격 | C29: =IF(C26="초과이익 가정",IF(F31="정배열",F28,F30),C28*(1+D26)) -> 56843.424 | E29: 10%씩 감소 | F29: =RIM계산!C12 -> 54233.553 | G29: =RIM계산!E12 -> 13.967595
B30: 매수가격 | C30: =IF(C26="초과이익 가정",IF(F31="정배열",F30,F28),C28*(1-D26)) -> 49792.041 | E30: 20%씩 감소 | F30: =RIM계산!C13 -> 56843.424 | G30: =RIM계산!E13 -> 14.639755
F31: =IF(F28>F30,"정배열","역배열") -> 역배열 | G31: =IF(F31="정배열","ROE>요구수익","ROE<요구수익") -> ROE<요구수익
B33: 기타 참고사항 | C33: =C21 -> 44166 | D33: =D21 -> 44531 | E33: =E21 -> 44896 | F33: =F21 -> 45261 | G33: =G21 -> 45627 | H33: 올해 예상배당
B34: 주당배당금 | C34: =Data!B43 -> 190 | D34: =Data!C43 -> 200 | E34: =Data!D43 -> 300 | F34: =Data!E43 -> 300 | G34: =Data!F43 -> 300 | H34: =Data!G43 -> 0
B35: 배당수익률 | C35: =Data!B44 -> 0.0163 | D35: =Data!C44 -> 0.0167 | E35: =Data!D44 -> 0.0101 | F35: =Data!E44 -> 0.0245 | G35: =Data!F44 -> 0.0269 | H35: =H34/C27 -> 0
B36: =Data!A39 -> ROA(%) | C36: =Data!B39 -> 0.0286 | D36: =Data!C39 -> 0.0435 | E36: =Data!D39 -> 0.0836 | F36: =Data!E39 -> 0.0533 | G36: =Data!F39 -> 0.0605 | H36: =Data!G39 -> 0.1017
B37: =Data!A41 -> EPS(원) | C37: =Data!B41 -> 1415 | D37: =Data!C41 -> 2280 | E37: =Data!D41 -> 4583 | F37: =Data!E41 -> 3033 | G37: =Data!F41 -> 3716 | H37: =Data!G41 -> 0
B38: =Data!A42 -> BPS(원) | C38: =Data!B42 -> 37224 | D38: =Data!C42 -> 39392 | E38: =Data!D42 -> 44218 | F38: =Data!E42 -> 46680 | G38: =Data!F42 -> 50003 | H38: =Data!G42 -> 0
B39: 배당성향(DPS/EPS) | C39: =C34/C38 -> 0.0051042338 | D39: =D34/D38 -> 0.005077173 | E39: =E34/E38 -> 0.0067845674 | F39: =F34/F38 -> 0.0064267352 | G39: =G34/G38 -> 0.00599964 | H39: =H34/H38 -> #DIV/0!
B41: 업종 비교 | C41: =Data!B84 -> 세방 | D41: =Data!C84 -> 코스피 전기,전자 | E41: =Data!D84 -> KOSPI
B42: ROE | C42: =Data!B85 -> 0.0781 | D42: =Data!C85 -> 0.1134 | E42: =Data!D85 -> 0.0747
B43: PER | C43: =Data!B86 -> 3 | D43: =Data!C86 -> 6.31 | E43: =Data!D86 -> 22.35
B44: 배당수익률 | C44: =Data!B87 -> 0.0269 | D44: =Data!C87 -> 0.028 | E44: =Data!D87 -> 0.0228
B46: 순이익 예측

Sheet Data
A2: 기초자료
A4: 종목명 | B4: =OFFSET(INDIRECT(H4),2,0,1,1) -> 세방 | F4: 이용안내 | G4: =MATCH(F4,FN_Snapshot!A:A,0) -> 24 | H4: ="FN_Snapshot!A"&G4 -> FN_Snapshot!A24
A5: 종가/ 전일대비 | B5: =LEFT(I5,SEARCHB("/",I5)-1)*1 -> 15770 | G5: =MATCH(A5,FN_Snapshot!A:A,0) -> 114 | H5: ="FN_Snapshot!A"&G5 -> FN_Snapshot!A114 | I5: =OFFSET(INDIRECT(H5),0,1,1,1) -> 15,770/
A6: 베타(1년) | B6: =I6 -> 0.54398 | G6: =MATCH(A6,FN_Snapshot!C:C,0) -> 117 | H6: ="FN_Snapshot!C"&G6 -> FN_Snapshot!C117 | I6: =OFFSET(INDIRECT(H6),0,1,1,1) -> 0.54398
A7: 발행주식수(보통주/ 우선주) | B7: =LEFT(I7,SEARCHB("/",I7)-1)*1 -> 19115603 | C7: =RIGHT(I7,LEN(I7)-SEARCHB("/",I7))*1 -> 3689250 | G7: =MATCH(A7,FN_Snapshot!A:A,0) -> 128 | H7: ="FN_Snapshot!A"&G7 -> FN_Snapshot!A128 | I7: =OFFSET(INDIRECT(H7),0,1,1,1) -> 19,115,603/ 3,689,250
A8: 자기주식 (자사주+자사주신탁) | B8: =I8 -> 784733 | G8: =MATCH(A8,FN_Snapshot!A:A,0) -> 185 | H8: ="FN_Snapshot!A"&G8 -> FN_Snapshot!A185 | I8: =OFFSET(INDIRECT(H8),0,2,1,1) -> 784733
A10: Business Summary | G10: =MATCH(A10,FN_Snapshot!A:A,0) -> 232 | H10: ="FN_Snapshot!A"&G10 -> FN_Snapshot!A232
A11: =OFFSET(INDIRECT(H$10),4,0,1,1) -> 반도체 호조로 사상 최대 분기 실적
A12: =OFFSET(INDIRECT(H$10),6,0,1,1) -> 한국 및 CE, IM부문 해외 9개 지역총괄과 DS부문 해외 5개 지역총괄, Harman 등 234개의 종속기업으로 구성된 글로벌 전자기업임. 세트사업에는 TV, 냉장고 등을 생산하는 CE부문과 스마트폰, 네트워크시스템, 컴퓨터 등을 생산하는 IM부문이 있음. 부품사업(DS부문)에서는 D램, 낸드 플래쉬, 모바일AP 등의 제품을 생산하는 반도체 사업과 TFT-LCD 및 OLED 디스플레이 패널을 생산하는 DP사업으로 구성됨.
A13: =OFFSET(INDIRECT(H$10),7,0,1,1) -> 메모리시장이 호황인 가운데 폴더블폰과 OLED 판매가 늘어나 3분기 매출액은 70조를 넘어서며 사상 최대의 실적을 달성함. 첨단공정 확대와 환율 영향으로 영업이익률도 20%를 넘어섬. 4분기 메모리시장은 당초 예상 대비 부품 수급 이슈 장기화에 따른 수요 리스크 확대가 우려됨. 북미 서버업체들의 반도체 재고가 3분기 대비 30% 이상 축소되며 반도체 재고 소진 속도가 예상을 상회하여 반도체 가격 반등 시점이 앞당겨질 전망임.
A15: 가치평가 지표
A16: PER | B16: =I16 -> 3 | G16: =MATCH(A16,FN_Snapshot!A:A,0) -> 51 | H16: ="FN_Snapshot!A"&G16 -> FN_Snapshot!A51 | I16: =OFFSET(INDIRECT(H16),1,0,1,1) -> 3
A17: 12M PER | B17: =I17 -> 10.55 | G17: =MATCH(A17,FN_Snapshot!A:A,0) -> 54 | H17: ="FN_Snapshot!A"&G17 -> FN_Snapshot!A54 | I17: =OFFSET(INDIRECT(H17),3,0,1,1) -> 10.55
A18: 업종 PER | B18: =I18 -> 6.31 | G18: =MATCH(A18,FN_Snapshot!A:A,0) -> 59 | H18: ="FN_Snapshot!A"&G18 -> FN_Snapshot!A59 | I18: =OFFSET(INDIRECT(H18),5,0,1,1) -> 6.31
A19: EV/EBITDA | B19: =I19 -> 4.09 | G19: =MATCH(A19,FN_Snapshot!A:A,0) -> 286 | H19: ="FN_Snapshot!A"&G19 -> FN_Snapshot!A286 | I19: =OFFSET(INDIRECT(H19),0,1,1,1) -> 4.09
A20: PBR | B20: =I20 -> 0.22 | G20: =MATCH(A20,FN_Snapshot!A:A,0) -> 70 | H20: ="FN_Snapshot!A"&G20 -> FN_Snapshot!A70 | I20: =OFFSET(INDIRECT(H20),1,0,1,1) -> 0.22
A21: 배당수익률 | B21: =I21 -> 0.0269 | G21: =MATCH(A21,FN_Snapshot!A:A,0) -> 73 | H21: ="FN_Snapshot!A"&G21 -> FN_Snapshot!A73 | I21: =OFFSET(INDIRECT(H21),4,0,1,1) -> 0.0269
A23: Financial Highlight
F24: (배당금(보통주,현금) / 시가총액(보통)) * 100 | G24: =MATCH(F24,FN_Snapshot!A:A,0) -> 406 | H24: ="FN_Snapshot!A"&G24 -> FN_Snapshot!A406 | I24: =OFFSET(INDIRECT($H$24),3,0,1,1) -> Financial Highlight
B25: 44166 | C25: 44531 | D25: 44896 | E25: 45261 | F25: 45627 | G25: 45992 | H25: 46357 | I25: 46722
A26: IFRS(연결) | B26: 2020 | C26: 2021 | D26: 2022 | E26: 2023 | F26: 2024 | G26: 2025 | H26: 2026 | I26: 2027
A27: =OFFSET(INDIRECT($H$24),ROW()-18,COLUMN()-1,1,1) -> 매출액 | B27: 8422 | C27: 10577 | D27: 12904 | E27: 11420 | F27: 13734
A28: =OFFSET(INDIRECT($H$24),ROW()-18,COLUMN()-1,1,1) -> 영업이익 | B28: 164 | C28: 292 | D28: 451 | E28: 287 | F28: 245
A29: =OFFSET(INDIRECT($H$24),ROW()-18,COLUMN()-1,1,1) -> 영업이익(발표기준) | B29: 164 | C29: 292 | D29: 451 | E29: 287 | F29: 245 | G29: =IF(OFFSET(INDIRECT($H$24),ROW()-18,COLUMN()-1,1,1)=0,"",OFFSET(INDIRECT($H$24),ROW()-18,COLUMN()-1,1,1)) | H29: =IF(OFFSET(INDIRECT($H$24),ROW()-18,COLUMN()-1,1,1)=0,"",OFFSET(INDIRECT($H$24),ROW()-18,COLUMN()-1,1,1)) | I29: =IF(OFFSET(INDIRECT($H$24),ROW()-18,COLUMN()-1,1,1)=0,"",OFFSET(INDIRECT($H$24),ROW()-18,COLUMN()-1,1,1))
A30: =OFFSET(INDIRECT($H$24),ROW()-18,COLUMN()-1,1,1) -> 당기순이익 | B30: 326 | C30: 524 | D30: 1055 | E30: 700 | F30: 855
A31: =OFFSET(INDIRECT($H$24),ROW()-18,COLUMN()-1,1,1) -> 지배주주순이익 | B31: 325 | C31: 524 | D31: 1054 | E31: 698 | F31: 855
A32: =OFFSET(INDIRECT($H$24),ROW()-18,COLUMN()-1,1,1) -> 비지배주주순이익 | B32: 1 | C32: 0 | D32: 1 | E32: 2 | F32: 0 | G32: =IF(OFFSET(INDIRECT($H$24),ROW()-18,COLUMN()-1,1,1)=0,"",OFFSET(INDIRECT($H$24),ROW()-18,COLUMN()-1,1,1)) | H32: =IF(OFFSET(INDIRECT($H$24),ROW()-18,COLUMN()-1,1,1)=0,"",OFFSET(INDIRECT($H$24),ROW()-18,COLUMN()-1,1,1)) | I32: =IF(OFFSET(INDIRECT($H$24),ROW()-18,COLUMN()-1,1,1)=0,"",OFFSET(INDIRECT($H$24),ROW()-18,COLUMN()-1,1,1))
A33: =OFFSET(INDIRECT($H$24),ROW()-18,COLUMN()-1,1,1) -> 자산총계 | B33: 11646 | C33: 12449 | D33: 12810 | E33: 13452 | F33: 14803 | G33: =IF(OFFSET(INDIRECT($H$24),ROW()-18,COLUMN()-1,1,1)=0,"",OFFSET(INDIRECT($H$24),ROW()-18,COLUMN()-1,1,1)) -> 4561023 | H33: =IF(OFFSET(INDIRECT($H$24),ROW()-18,COLUMN()-1,1,1)=0,"",OFFSET(INDIRECT($H$24),ROW()-18,COLUMN()-1,1,1)) -> 4996128 | I33: =IF(OFFSET(INDIRECT($H$24),ROW()-18,COLUMN()-1,1,1)=0,"",OFFSET(INDIRECT($H$24),ROW()-18,COLUMN()-1,1,1))
A34: =OFFSET(INDIRECT($H$24),ROW()-18,COLUMN()-1,1,1) -> 부채총계 | B34: 3112 | C34: 3478 | D34: 2775 | E34: 2870 | F34: 3457 | G34: =IF(OFFSET(INDIRECT($H$24),ROW()-18,COLUMN()-1,1,1)=0,"",OFFSET(INDIRECT($H$24),ROW()-18,COLUMN()-1,1,1)) -> 1194703 | H34: =IF(OFFSET(INDIRECT($H$24),ROW()-18,COLUMN()-1,1,1)=0,"",OFFSET(INDIRECT($H$24),ROW()-18,COLUMN()-1,1,1)) -> 1240494 | I34: =IF(OFFSET(INDIRECT($H$24),ROW()-18,COLUMN()-1,1,1)=0,"",OFFSET(INDIRECT($H$24),ROW()-18,COLUMN()-1,1,1))
A35: =OFFSET(INDIRECT($H$24),ROW()-18,COLUMN()-1,1,1) -> 자본총계 | B35: 8534 | C35: 8972 | D35: 10035 | E35: 10582 | F35: 11346 | G35: =IF(OFFSET(INDIRECT($H$24),ROW()-18,COLUMN()-1,1,1)=0,"",OFFSET(INDIRECT($H$24),ROW()-18,COLUMN()-1,1,1)) -> 3366321 | H35: =IF(OFFSET(INDIRECT($H$24),ROW()-18,COLUMN()-1,1,1)=0,"",OFFSET(INDIRECT($H$24),ROW()-18,COLUMN()-1,1,1)) -> 3755639 | I35: =IF(OFFSET(INDIRECT($H$24),ROW()-18,COLUMN()-1,1,1)=0,"",OFFSET(INDIRECT($H$24),ROW()-18,COLUMN()-1,1,1))
A36: =OFFSET(INDIRECT($H$24),ROW()-18,COLUMN()-1,1,1) -> 지배주주지분 | B36: 8505 | C36: 8943 | D36: 10007 | E36: 10564 | F36: 11329
A37: =OFFSET(INDIRECT($H$24),ROW()-18,COLUMN()-1,1,1) -> 비지배주주지분 | B37: 30 | C37: 29 | D37: 28 | E37: 19 | F37: 17 | G37: =IF(OFFSET(INDIRECT($H$24),ROW()-18,COLUMN()-1,1,1)=0,"",OFFSET(INDIRECT($H$24),ROW()-18,COLUMN()-1,1,1)) -> 99222 | H37: =IF(OFFSET(INDIRECT($H$24),ROW()-18,COLUMN()-1,1,1)=0,"",OFFSET(INDIRECT($H$24),ROW()-18,COLUMN()-1,1,1)) -> 111326 | I37: =IF(OFFSET(INDIRECT($H$24),ROW()-18,COLUMN()-1,1,1)=0,"",OFFSET(INDIRECT($H$24),ROW()-18,COLUMN()-1,1,1))
A38: =OFFSET(INDIRECT($H$24),ROW()-18,COLUMN()-1,1,1) -> 자본금 | B38: 115 | C38: 115 | D38: 115 | E38: 115 | F38: 115 | G38: =IF(OFFSET(INDIRECT($H$24),ROW()-18,COLUMN()-1,1,1)=0,"",OFFSET(INDIRECT($H$24),ROW()-18,COLUMN()-1,1,1)) -> 8979 | H38: =IF(OFFSET(INDIRECT($H$24),ROW()-18,COLUMN()-1,1,1)=0,"",OFFSET(INDIRECT($H$24),ROW()-18,COLUMN()-1,1,1)) -> 8979 | I38: =IF(OFFSET(INDIRECT($H$24),ROW()-18,COLUMN()-1,1,1)=0,"",OFFSET(INDIRECT($H$24),ROW()-18,COLUMN()-1,1,1))
A39: =OFFSET(INDIRECT($H$24),ROW()-2,COLUMN()-1,1,1) -> ROA(%) | B39: =OFFSET(INDIRECT($H$24),ROW()-2,COLUMN()-1,1,1)/100 -> 0.0286 | C39: =OFFSET(INDIRECT($H$24),ROW()-2,COLUMN()-1,1,1)/100 -> 0.0435 | D39: =OFFSET(INDIRECT($H$24),ROW()-2,COLUMN()-1,1,1)/100 -> 0.0836 | E39: =OFFSET(INDIRECT($H$24),ROW()-2,COLUMN()-1,1,1)/100 -> 0.0533 | F39: =OFFSET(INDIRECT($H$24),ROW()-2,COLUMN()-1,1,1)/100 -> 0.0605 | G39: =IF(OFFSET(INDIRECT($H$24),ROW()-2,COLUMN()-1,1,1)=0,"",OFFSET(INDIRECT($H$24),ROW()-2,COLUMN()-1,1,1)/100) -> 0.1017 | H39: =IF(OFFSET(INDIRECT($H$24),ROW()-2,COLUMN()-1,1,1)=0,"",OFFSET(INDIRECT($H$24),ROW()-2,COLUMN()-1,1,1)/100) -> 0.11 | I39: =IF(OFFSET(INDIRECT($H$24),ROW()-2,COLUMN()-1,1,1)=0,"",OFFSET(INDIRECT($H$24),ROW()-2,COLUMN()-1,1,1)/100) -> 0.1171
A40: =OFFSET(INDIRECT($H$24),ROW()+1,COLUMN()-1,1,1) -> ROE(%) | B40: 0.0389 | C40: 0.0601 | D40: 0.1112 | E40: 0.0678 | F40: 0.0781
A41: =OFFSET(INDIRECT($H$24),ROW()+4,COLUMN()-1,1,1) -> EPS(원) | B41: 1415 | C41: 2280 | D41: 4583 | E41: 3033 | F41: 3716
A42: =OFFSET(INDIRECT($H$24),ROW()+7,COLUMN()-1,1,1) -> BPS(원) | B42: 37224 | C42: 39392 | D42: 44218 | E42: 46680 | F42: 50003
A43: =OFFSET(INDIRECT($H$24),ROW()+10,COLUMN()-1,1,1) -> DPS(원) | B43: 190 | C43: 200 | D43: 300 | E43: 300 | F43: 300
A44: =OFFSET(INDIRECT($H$24),ROW()+22,COLUMN()-1,1,1) -> 배당수익률(%) | B44: 0.0163 | C44: 0.0167 | D44: 0.0101 | E44: 0.0245 | F44: 0.0269
A50: IFRS(연결) | B50: =OFFSET(INDIRECT($H$24),72,1,1,1) -> 45717 | C50: =OFFSET(INDIRECT($H$24),72,2,1,1) -> 45809 | D50: =OFFSET(INDIRECT($H$24),72,3,1,1) -> 45901 | E50: =OFFSET(INDIRECT($H$24),72,4,1,1) -> 45992 | F50: =OFFSET(INDIRECT($H$24),72,5,1,1) -> 45992 | K50: =MONTH(F50) -> 12
A51: =OFFSET(INDIRECT($H$24),ROW()+25,COLUMN()-1,1,1) -> 매출액 | B51: =OFFSET(INDIRECT($H$24),ROW()+25,COLUMN()-1,1,1) -> 3254 | C51: =OFFSET(INDIRECT($H$24),ROW()+25,COLUMN()-1,1,1) -> 3266 | D51: =OFFSET(INDIRECT($H$24),ROW()+25,COLUMN()-1,1,1) -> 3155 | E51: =OFFSET(INDIRECT($H$24),ROW()+25,COLUMN()-1,1,1) -> 3155 | F51: =OFFSET(INDIRECT($H$24),ROW()+25,COLUMN()-1,1,1) -> 3155 | G51: =OFFSET(INDIRECT($H$24),ROW()+25,COLUMN()-1,1,1) -> 742191 | H51: =OFFSET(INDIRECT($H$24),ROW()+25,COLUMN()-1,1,1) -> 736359 | I51: =OFFSET(INDIRECT($H$24),ROW()+25,COLUMN()-1,1,1) -> 815194 | K51: =MIN(B51:F51,B60:F60) -> 3155
A52: =OFFSET(INDIRECT($H$24),ROW()+25,COLUMN()-1,1,1) -> 영업이익 | B52: =OFFSET(INDIRECT($H$24),ROW()+25,COLUMN()-1,1,1) -> 107 | C52: =OFFSET(INDIRECT($H$24),ROW()+25,COLUMN()-1,1,1) -> 116 | D52: =OFFSET(INDIRECT($H$24),ROW()+25,COLUMN()-1,1,1) -> 73 | E52: =OFFSET(INDIRECT($H$24),ROW()+25,COLUMN()-1,1,1) -> 73 | F52: =OFFSET(INDIRECT($H$24),ROW()+25,COLUMN()-1,1,1) -> 73 | G52: =OFFSET(INDIRECT($H$24),ROW()+25,COLUMN()-1,1,1) -> 130350 | H52: =OFFSET(INDIRECT($H$24),ROW()+25,COLUMN()-1,1,1) -> 133921 | I52: =OFFSET(INDIRECT($H$24),ROW()+25,COLUMN()-1,1,1) -> 160374
A53: =OFFSET(INDIRECT($H$24),ROW()+25,COLUMN()-1,1,1) -> 영업이익(발표기준) | B53: =OFFSET(INDIRECT($H$24),ROW()+25,COLUMN()-1,1,1) -> 107 | C53: =OFFSET(INDIRECT($H$24),ROW()+25,COLUMN()-1,1,1) -> 116 | D53: =OFFSET(INDIRECT($H$24),ROW()+25,COLUMN()-1,1,1) -> 73 | E53: =OFFSET(INDIRECT($H$24),ROW()+25,COLUMN()-1,1,1) -> 73 | F53: =OFFSET(INDIRECT($H$24),ROW()+25,COLUMN()-1,1,1) -> 73 | G53: =OFFSET(INDIRECT($H$24),ROW()+25,COLUMN()-1,1,1) -> 0 | H53: =OFFSET(INDIRECT($H$24),ROW()+25,COLUMN()-1,1,1) -> 0 | I53: =OFFSET(INDIRECT($H$24),ROW()+25,COLUMN()-1,1,1) -> 0
A54: =OFFSET(INDIRECT($H$24),ROW()+25,COLUMN()-1,1,1) -> 당기순이익 | B54: =OFFSET(INDIRECT($H$24),ROW()+25,COLUMN()-1,1,1) -> 280 | C54: =OFFSET(INDIRECT($H$24),ROW()+25,COLUMN()-1,1,1) -> 174 | D54: =OFFSET(INDIRECT($H$24),ROW()+25,COLUMN()-1,1,1) -> 116 | E54: =OFFSET(INDIRECT($H$24),ROW()+25,COLUMN()-1,1,1) -> 116 | F54: =OFFSET(INDIRECT($H$24),ROW()+25,COLUMN()-1,1,1) -> 116 | G54: =OFFSET(INDIRECT($H$24),ROW()+25,COLUMN()-1,1,1) -> 94986 | H54: =OFFSET(INDIRECT($H$24),ROW()+25,COLUMN()-1,1,1) -> 98185 | I54: =OFFSET(INDIRECT($H$24),ROW()+25,COLUMN()-1,1,1) -> 122210 | K54: 4분기 합
A55: =OFFSET(INDIRECT($H$24),ROW()+25,COLUMN()-1,1,1) -> 지배주주순이익 | B55: =OFFSET(INDIRECT($H$24),ROW()+25,COLUMN()-1,1,1) -> 280 | C55: =OFFSET(INDIRECT($H$24),ROW()+25,COLUMN()-1,1,1) -> 174 | D55: =OFFSET(INDIRECT($H$24),ROW()+25,COLUMN()-1,1,1) -> 116 | E55: =OFFSET(INDIRECT($H$24),ROW()+25,COLUMN()-1,1,1) -> 116 | F55: =OFFSET(INDIRECT($H$24),ROW()+25,COLUMN()-1,1,1) -> 116 | G55: =OFFSET(INDIRECT($H$24),ROW()+25,COLUMN()-1,1,1) -> 98347 | H55: =OFFSET(INDIRECT($H$24),ROW()+25,COLUMN()-1,1,1) -> 96976 | I55: =OFFSET(INDIRECT($H$24),ROW()+25,COLUMN()-1,1,1) -> 114404 | K55: =SUM(C55:F55) -> 522
A56: =OFFSET(INDIRECT($H$24),ROW()+25,COLUMN()-1,1,1) -> 비지배주주순이익 | B56: =OFFSET(INDIRECT($H$24),ROW()+25,COLUMN()-1,1,1) -> 0 | C56: =OFFSET(INDIRECT($H$24),ROW()+25,COLUMN()-1,1,1) -> 0 | D56: =OFFSET(INDIRECT($H$24),ROW()+25,COLUMN()-1,1,1) -> 0 | E56: =OFFSET(INDIRECT($H$24),ROW()+25,COLUMN()-1,1,1) -> 0 | F56: =OFFSET(INDIRECT($H$24),ROW()+25,COLUMN()-1,1,1) -> 0 | G56: =OFFSET(INDIRECT($H$24),ROW()+25,COLUMN()-1,1,1) -> 0 | H56: =OFFSET(INDIRECT($H$24),ROW()+25,COLUMN()-1,1,1) -> 0 | I56: =OFFSET(INDIRECT($H$24),ROW()+25,COLUMN()-1,1,1) -> 0
A57: =OFFSET(INDIRECT($H$24),ROW()+25,COLUMN()-1,1,1) -> 자산총계 | B57: =OFFSET(INDIRECT($H$24),ROW()+25,COLUMN()-1,1,1) -> 14637 | C57: =OFFSET(INDIRECT($H$24),ROW()+25,COLUMN()-1,1,1) -> 14769 | D57: =OFFSET(INDIRECT($H$24),ROW()+25,COLUMN()-1,1,1) -> 14897 | E57: =OFFSET(INDIRECT($H$24),ROW()+25,COLUMN()-1,1,1) -> 14897 | F57: =OFFSET(INDIRECT($H$24),ROW()+25,COLUMN()-1,1,1) -> 14897 | G57: =OFFSET(INDIRECT($H$24),ROW()+25,COLUMN()-1,1,1) -> 0 | H57: =OFFSET(INDIRECT($H$24),ROW()+25,COLUMN()-1,1,1) -> 0 | I57: =OFFSET(INDIRECT($H$24),ROW()+25,COLUMN()-1,1,1) -> 0
A58: =OFFSET(INDIRECT($H$24),ROW()+25,COLUMN()-1,1,1) -> 부채총계 | B58: =OFFSET(INDIRECT($H$24),ROW()+25,COLUMN()-1,1,1) -> 3066 | C58: =OFFSET(INDIRECT($H$24),ROW()+25,COLUMN()-1,1,1) -> 2981 | D58: =OFFSET(INDIRECT($H$24),ROW()+25,COLUMN()-1,1,1) -> 2923 | E58: =OFFSET(INDIRECT($H$24),ROW()+25,COLUMN()-1,1,1) -> 2923 | F58: =OFFSET(INDIRECT($H$24),ROW()+25,COLUMN()-1,1,1) -> 2923 | G58: =OFFSET(INDIRECT($H$24),ROW()+25,COLUMN()-1,1,1) -> 0 | H58: =OFFSET(INDIRECT($H$24),ROW()+25,COLUMN()-1,1,1) -> 0 | I58: =OFFSET(INDIRECT($H$24),ROW()+25,COLUMN()-1,1,1) -> 0
A59: =OFFSET(INDIRECT($H$24),ROW()+25,COLUMN()-1,1,1) -> 자본총계 | B59: =OFFSET(INDIRECT($H$24),ROW()+25,COLUMN()-1,1,1) -> 11571 | C59: =OFFSET(INDIRECT($H$24),ROW()+25,COLUMN()-1,1,1) -> 11788 | D59: =OFFSET(INDIRECT($H$24),ROW()+25,COLUMN()-1,1,1) -> 11974 | E59: =OFFSET(INDIRECT($H$24),ROW()+25,COLUMN()-1,1,1) -> 11974 | F59: =OFFSET(INDIRECT($H$24),ROW()+25,COLUMN()-1,1,1) -> 11974 | G59: =OFFSET(INDIRECT($H$24),ROW()+25,COLUMN()-1,1,1) -> 0 | H59: =OFFSET(INDIRECT($H$24),ROW()+25,COLUMN()-1,1,1) -> 0 | I59: =OFFSET(INDIRECT($H$24),ROW()+25,COLUMN()-1,1,1) -> 0
A60: =OFFSET(INDIRECT($H$24),ROW()+25,COLUMN()-1,1,1) -> 지배주주지분 | B60: =OFFSET(INDIRECT($H$24),ROW()+25,COLUMN()-1,1,1) -> 11553 | C60: =OFFSET(INDIRECT($H$24),ROW()+25,COLUMN()-1,1,1) -> 11769 | D60: =OFFSET(INDIRECT($H$24),ROW()+25,COLUMN()-1,1,1) -> 11956 | E60: =OFFSET(INDIRECT($H$24),ROW()+25,COLUMN()-1,1,1) -> 11956 | F60: =OFFSET(INDIRECT($H$24),ROW()+25,COLUMN()-1,1,1) -> 11956 | G60: =OFFSET(INDIRECT($H$24),ROW()+25,COLUMN()-1,1,1) -> 0 | H60: =OFFSET(INDIRECT($H$24),ROW()+25,COLUMN()-1,1,1) -> 0 | I60: =OFFSET(INDIRECT($H$24),ROW()+25,COLUMN()-1,1,1) -> 0 | K60: =AVERAGE(B60,F60) -> 11754.5
A61: =OFFSET(INDIRECT($H$24),ROW()+25,COLUMN()-1,1,1) -> 비지배주주지분 | B61: =OFFSET(INDIRECT($H$24),ROW()+25,COLUMN()-1,1,1) -> 18 | C61: =OFFSET(INDIRECT($H$24),ROW()+25,COLUMN()-1,1,1) -> 19 | D61: =OFFSET(INDIRECT($H$24),ROW()+25,COLUMN()-1,1,1) -> 18 | E61: =OFFSET(INDIRECT($H$24),ROW()+25,COLUMN()-1,1,1) -> 18 | F61: =OFFSET(INDIRECT($H$24),ROW()+25,COLUMN()-1,1,1) -> 18 | G61: =OFFSET(INDIRECT($H$24),ROW()+25,COLUMN()-1,1,1) -> 0 | H61: =OFFSET(INDIRECT($H$24),ROW()+25,COLUMN()-1,1,1) -> 0 | I61: =OFFSET(INDIRECT($H$24),ROW()+25,COLUMN()-1,1,1) -> 0 | K61: =IF(K51=0,K60/K51,K55/K60) -> 0.044408524
A62: =OFFSET(INDIRECT($H$24),ROW()+25,COLUMN()-1,1,1) -> 자본금 | B62: =OFFSET(INDIRECT($H$24),ROW()+25,COLUMN()-1,1,1) -> 115 | C62: =OFFSET(INDIRECT($H$24),ROW()+25,COLUMN()-1,1,1) -> 115 | D62: =OFFSET(INDIRECT($H$24),ROW()+25,COLUMN()-1,1,1) -> 115 | E62: =OFFSET(INDIRECT($H$24),ROW()+25,COLUMN()-1,1,1) -> 115 | F62: =OFFSET(INDIRECT($H$24),ROW()+25,COLUMN()-1,1,1) -> 115 | G62: =OFFSET(INDIRECT($H$24),ROW()+25,COLUMN()-1,1,1) -> 0 | H62: =OFFSET(INDIRECT($H$24),ROW()+25,COLUMN()-1,1,1) -> 0 | I62: =OFFSET(INDIRECT($H$24),ROW()+25,COLUMN()-1,1,1) -> 0
F66: IFRS(별도) | G66: =IF(ISNA(MATCH(F66,FN_Snapshot!A:A,0)),MATCH(F67,FN_Snapshot!A:A,0),MATCH(F66,FN_Snapshot!A:A,0)) -> 544 | H66: ="FN_Snapshot!A"&G66 -> FN_Snapshot!A544 | I66: =OFFSET(INDIRECT($H$66),3,0,1,1) -> 0
F67: GAAP(개별)
A68: =OFFSET(INDIRECT($H$66),0,0,1,1) -> IFRS(별도) | B68: =OFFSET(INDIRECT($H$66),127,1,1,1) -> 44166 | C68: =OFFSET(INDIRECT($H$66),127,2,1,1) -> 44256 | D68: =OFFSET(INDIRECT($H$66),127,3,1,1) -> 44348 | E68: =OFFSET(INDIRECT($H$66),127,4,1,1) -> 44440 | F68: =OFFSET(INDIRECT($H$66),127,5,1,1) -> 44531 | K68: =MONTH(F68) -> 12
A69: =OFFSET(INDIRECT($H$66),ROW()+62,COLUMN()-1,1,1) -> 매출액 | B69: =OFFSET(INDIRECT($H$66),ROW()+62,COLUMN()-1,1,1) -> 405179 | C69: =OFFSET(INDIRECT($H$66),ROW()+62,COLUMN()-1,1,1) -> 450424 | D69: =OFFSET(INDIRECT($H$66),ROW()+62,COLUMN()-1,1,1) -> 457686 | E69: =OFFSET(INDIRECT($H$66),ROW()+62,COLUMN()-1,1,1) -> 539198 | F69: =OFFSET(INDIRECT($H$66),ROW()+62,COLUMN()-1,1,1) -> 550139 | G69: =OFFSET(INDIRECT($H$66),ROW()+62,COLUMN()-1,1,1) -> 0 | H69: =OFFSET(INDIRECT($H$66),ROW()+62,COLUMN()-1,1,1) -> 0 | I69: =OFFSET(INDIRECT($H$66),ROW()+62,COLUMN()-1,1,1) -> 0 | K69: =MIN(B69:F69,B75:F75) -> 405179
A70: =OFFSET(INDIRECT($H$66),ROW()+62,COLUMN()-1,1,1) -> 영업이익 | B70: =OFFSET(INDIRECT($H$66),ROW()+62,COLUMN()-1,1,1) -> 58023 | C70: =OFFSET(INDIRECT($H$66),ROW()+62,COLUMN()-1,1,1) -> 44455 | D70: =OFFSET(INDIRECT($H$66),ROW()+62,COLUMN()-1,1,1) -> 77188 | E70: =OFFSET(INDIRECT($H$66),ROW()+62,COLUMN()-1,1,1) -> 105812 | F70: =OFFSET(INDIRECT($H$66),ROW()+62,COLUMN()-1,1,1) -> 92478 | G70: =OFFSET(INDIRECT($H$66),ROW()+62,COLUMN()-1,1,1) -> 0 | H70: =OFFSET(INDIRECT($H$66),ROW()+62,COLUMN()-1,1,1) -> 0 | I70: =OFFSET(INDIRECT($H$66),ROW()+62,COLUMN()-1,1,1) -> 0
A71: =OFFSET(INDIRECT($H$66),ROW()+62,COLUMN()-1,1,1) -> 영업이익(발표기준) | B71: =OFFSET(INDIRECT($H$66),ROW()+62,COLUMN()-1,1,1) -> 58023 | C71: =OFFSET(INDIRECT($H$66),ROW()+62,COLUMN()-1,1,1) -> 44455 | D71: =OFFSET(INDIRECT($H$66),ROW()+62,COLUMN()-1,1,1) -> 77188 | E71: =OFFSET(INDIRECT($H$66),ROW()+62,COLUMN()-1,1,1) -> 105812 | F71: =OFFSET(INDIRECT($H$66),ROW()+62,COLUMN()-1,1,1) -> 92478 | G71: =OFFSET(INDIRECT($H$66),ROW()+62,COLUMN()-1,1,1) -> 0 | H71: =OFFSET(INDIRECT($H$66),ROW()+62,COLUMN()-1,1,1) -> 0 | I71: =OFFSET(INDIRECT($H$66),ROW()+62,COLUMN()-1,1,1) -> 0 | K71: 4분기 합
A72: =OFFSET(INDIRECT($H$66),ROW()+62,COLUMN()-1,1,1) -> 당기순이익 | B72: =OFFSET(INDIRECT($H$66),ROW()+62,COLUMN()-1,1,1) -> 45168 | C72: =OFFSET(INDIRECT($H$66),ROW()+62,COLUMN()-1,1,1) -> 45476 | D72: =OFFSET(INDIRECT($H$66),ROW()+62,COLUMN()-1,1,1) -> 91292 | E72: =OFFSET(INDIRECT($H$66),ROW()+62,COLUMN()-1,1,1) -> 85947 | F72: =OFFSET(INDIRECT($H$66),ROW()+62,COLUMN()-1,1,1) -> 86995 | G72: =OFFSET(INDIRECT($H$66),ROW()+62,COLUMN()-1,1,1) -> 0 | H72: =OFFSET(INDIRECT($H$66),ROW()+62,COLUMN()-1,1,1) -> 0 | I72: =OFFSET(INDIRECT($H$66),ROW()+62,COLUMN()-1,1,1) -> 0 | K72: =SUM(C72:F72) -> 309710
A73: =OFFSET(INDIRECT($H$66),ROW()+62,COLUMN()-1,1,1) -> 자산총계 | B73: =OFFSET(INDIRECT($H$66),ROW()+62,COLUMN()-1,1,1) -> 2296644 | C73: =OFFSET(INDIRECT($H$66),ROW()+62,COLUMN()-1,1,1) -> 2365306 | D73: =OFFSET(INDIRECT($H$66),ROW()+62,COLUMN()-1,1,1) -> 2278276 | E73: =OFFSET(INDIRECT($H$66),ROW()+62,COLUMN()-1,1,1) -> 2406844 | F73: =OFFSET(INDIRECT($H$66),ROW()+62,COLUMN()-1,1,1) -> 2511122 | G73: =OFFSET(INDIRECT($H$66),ROW()+62,COLUMN()-1,1,1) -> 0 | H73: =OFFSET(INDIRECT($H$66),ROW()+62,COLUMN()-1,1,1) -> 0 | I73: =OFFSET(INDIRECT($H$66),ROW()+62,COLUMN()-1,1,1) -> 0
A74: =OFFSET(INDIRECT($H$66),ROW()+62,COLUMN()-1,1,1) -> 부채총계 | B74: =OFFSET(INDIRECT($H$66),ROW()+62,COLUMN()-1,1,1) -> 463477 | C74: =OFFSET(INDIRECT($H$66),ROW()+62,COLUMN()-1,1,1) -> 617745 | D74: =OFFSET(INDIRECT($H$66),ROW()+62,COLUMN()-1,1,1) -> 464747 | E74: =OFFSET(INDIRECT($H$66),ROW()+62,COLUMN()-1,1,1) -> 532943 | F74: =OFFSET(INDIRECT($H$66),ROW()+62,COLUMN()-1,1,1) -> 579185 | G74: =OFFSET(INDIRECT($H$66),ROW()+62,COLUMN()-1,1,1) -> 0 | H74: =OFFSET(INDIRECT($H$66),ROW()+62,COLUMN()-1,1,1) -> 0 | I74: =OFFSET(INDIRECT($H$66),ROW()+62,COLUMN()-1,1,1) -> 0
A75: =OFFSET(INDIRECT($H$66),ROW()+62,COLUMN()-1,1,1) -> 자본총계 | B75: =OFFSET(INDIRECT($H$66),ROW()+62,COLUMN()-1,1,1) -> 1833167 | C75: =OFFSET(INDIRECT($H$66),ROW()+62,COLUMN()-1,1,1) -> 1747561 | D75: =OFFSET(INDIRECT($H$66),ROW()+62,COLUMN()-1,1,1) -> 1813529 | E75: =OFFSET(INDIRECT($H$66),ROW()+62,COLUMN()-1,1,1) -> 1873901 | F75: =OFFSET(INDIRECT($H$66),ROW()+62,COLUMN()-1,1,1) -> 1931937 | G75: =OFFSET(INDIRECT($H$66),ROW()+62,COLUMN()-1,1,1) -> 0 | H75: =OFFSET(INDIRECT($H$66),ROW()+62,COLUMN()-1,1,1) -> 0 | I75: =OFFSET(INDIRECT($H$66),ROW()+62,COLUMN()-1,1,1) -> 0 | K75: =AVERAGE(B75,F75) -> 1882552
A76: =OFFSET(INDIRECT($H$66),ROW()+62,COLUMN()-1,1,1) -> 자본금 | B76: =OFFSET(INDIRECT($H$66),ROW()+62,COLUMN()-1,1,1) -> 8975 | C76: =OFFSET(INDIRECT($H$66),ROW()+62,COLUMN()-1,1,1) -> 8975 | D76: =OFFSET(INDIRECT($H$66),ROW()+62,COLUMN()-1,1,1) -> 8975 | E76: =OFFSET(INDIRECT($H$66),ROW()+62,COLUMN()-1,1,1) -> 8975 | F76: =OFFSET(INDIRECT($H$66),ROW()+62,COLUMN()-1,1,1) -> 8975 | G76: =OFFSET(INDIRECT($H$66),ROW()+62,COLUMN()-1,1,1) -> 0 | H76: =OFFSET(INDIRECT($H$66),ROW()+62,COLUMN()-1,1,1) -> 0 | I76: =OFFSET(INDIRECT($H$66),ROW()+62,COLUMN()-1,1,1) -> 0 | K76: =K72/K75 -> 0.16451604
K78: =IF(ISERR(K61),IF(K69=0,"분기자료부족",K76),K61) -> 0.044408524
A82: 업종 비교 | G82: =MATCH(A82,FN_Snapshot!A:A,0) -> 271 | H82: ="FN_Snapshot!A"&G82 -> FN_Snapshot!A271
A84: 구분 | B84: 세방 | C84: =OFFSET(INDIRECT($H$82),6,2,1,1) -> 코스피 전기,전자 | D84: =OFFSET(INDIRECT($H$82),6,3,1,1) -> KOSPI
A85: ROE | B85: 0.0781 | C85: 0.1134 | D85: 0.0747
A86: PER | B86: 3 | C86: 6.31 | D86: =OFFSET(INDIRECT($H$82),11,3,1,1) -> 22.35
A87: 배당수익률 | B87: 0.0269 | C87: 0.028 | D87: 0.0228

Sheet RIM계산
A2: 최근 결산연도 | B2: =Data!F26 -> 2024 | D2: ROE | E2: =Data!B40 -> 0.0389 | F2: =Data!C40 -> 0.0601 | G2: =Data!D40 -> 0.1112 | H2: =Data!E40 -> 0.0678 | I2: =Data!F40 -> 0.0781 | J2: =Data!G40 -> 0 | K2: =Data!H40 -> 0 | L2: =Data!I40 -> 0 | M2: =Data!K78 -> 0.044408524
A3: 요구수익률 | B3: =결과!D14 -> 0.1026 | D3: 지배주주지분 | E3: =Data!B36 -> 8505 | F3: =Data!C36 -> 8943 | G3: =Data!D36 -> 10007 | H3: =Data!E36 -> 10564 | I3: =Data!F36 -> 11329 | J3: =Data!G36 -> 0 | K3: =Data!H36 -> 0 | L3: =Data!I36 -> 0 | M3: =IF(ISERR(Data!K61),IF(Data!K69=0,Data!F36,Data!F75),Data!F60) -> 11956
A4: 발행주식수(보통+우선) | B4: =Data!B7+Data!C7 -> 22804853 | D4: 년도 | E4: =DATE(Data!B26,12,31) -> 44196 | F4: =DATE(Data!C26,12,31) -> 44561 | G4: =DATE(Data!D26,12,31) -> 44926 | H4: =DATE(Data!E26,12,31) -> 45291 | I4: =DATE(Data!F26,12,31) -> 45657 | J4: =DATE(Data!G26,12,31) -> 46022 | K4: =DATE(Data!H26,12,31) -> 46387 | L4: =DATE(Data!I26,12,31) -> 46752 | M4: =EOMONTH(Data!F50,0) -> 46022
A5: 자기주식 | B5: =Data!B8 -> 784733 | D5: 지배주주순이익 | E5: =Data!B31 -> 325 | F5: =Data!C31 -> 524 | G5: =Data!D31 -> 1054 | H5: =Data!E31 -> 698 | I5: =Data!F31 -> 855 | J5: =Data!G31 -> 0 | K5: =Data!H31 -> 0 | L5: =Data!I31 -> 0 | M5: =IF(ISERR(Data!K61),IF(Data!K69=0,Data!F31,Data!K72),Data!K55) -> 522
A7: ROE 추정 | B7: =결과!D20 -> 0.080183333 | E7: 분석기준시점 | F7: 45657 | G7: 현재 | H7: =TODAY() -> 46101 | I7: 분석종료시점 | J7: 2034
E8: 기준시점 주주지분 | F8: =IF(ISNA(HLOOKUP(B7,$E$2:$M$3,2,FALSE)),M3,HLOOKUP(B7,$E$2:$M$3,2,FALSE)) -> 11956 | G8: 기준시점-현재 | H8: =F7-H7 -> -444
A10: 초과이익 가정 | B10: 적정주주가치 | C10: 적정주가 | D10: 판단 | E10: PER
A11: 지속 | B11: =C25 -> 10964.267 | C11: =C26 -> 49792.041 | D11: 매도가격 | E11: =B11/$I$5 -> 12.823704
A12: 10%씩 감소 | B12: =C38 -> 11942.294 | C12: =C39 -> 54233.553 | D12: 적정가격 | E12: =B12/$I$5 -> 13.967595
A13: 20%씩 감소 | B13: =C51 -> 12516.99 | C13: =C52 -> 56843.424 | D13: 매수가격 | E13: =B13/$I$5 -> 14.639755
A15: 초과이익 지속계수 | B15: 1
A16: 시점 | B16: =$F$7 -> 45657 | C16: =B16+365 -> 46022 | D16: =C16+365 -> 46387 | E16: =D16+365 -> 46752 | F16: =E16+365 -> 47117 | G16: =F16+365 -> 47482 | H16: =G16+365 -> 47847 | I16: =H16+365 -> 48212 | J16: =I16+365 -> 48577 | ... L16: =K16+365 -> 49307
A17: 요구수익률 | B17: =$B$3 -> 0.1026 | C17: =B17 -> 0.1026 | D17: =C17 -> 0.1026 | E17: =D17 -> 0.1026 | F17: =E17 -> 0.1026 | G17: =F17 -> 0.1026 | H17: =G17 -> 0.1026 | I17: =H17 -> 0.1026 | J17: =I17 -> 0.1026 | ... L17: =K17 -> 0.1026
A18: 초과이익률 | B18: =$B$7-B17 -> -0.022416667 | C18: =IF(YEAR(C16)>$J$7,0,B18*$B$15) -> -0.022416667 | D18: =IF(YEAR(D16)>$J$7,0,C18*$B$15) -> -0.022416667 | E18: =IF(YEAR(E16)>$J$7,0,D18*$B$15) -> -0.022416667 | F18: =IF(YEAR(F16)>$J$7,0,E18*$B$15) -> -0.022416667 | G18: =IF(YEAR(G16)>$J$7,0,F18*$B$15) -> -0.022416667 | H18: =IF(YEAR(H16)>$J$7,0,G18*$B$15) -> -0.022416667 | I18: =IF(YEAR(I16)>$J$7,0,H18*$B$15) -> -0.022416667 | J18: =IF(YEAR(J16)>$J$7,0,I18*$B$15) -> -0.022416667 | ... L18: =IF(YEAR(L16)>$J$7,0,K18*$B$15) -> -0.022416667
A19: ROE | B19: =B17+B18 -> 0.080183333 | C19: =C17+C18 -> 0.080183333 | D19: =D17+D18 -> 0.080183333 | E19: =E17+E18 -> 0.080183333 | F19: =F17+F18 -> 0.080183333 | G19: =G17+G18 -> 0.080183333 | H19: =H17+H18 -> 0.080183333 | I19: =I17+I18 -> 0.080183333 | ... L19: =L17+L18 -> 0.080183333
A20: 지배주주순이익 | C20: =B21*C19 -> 958.67193 | D20: =C21*D19 -> 1035.5414 | E20: =D21*E19 -> 1118.5746 | F20: =E21*F19 -> 1208.2657 | G20: =F21*G19 -> 1305.1484 | H20: =G21*H19 -> 1409.7996 | I20: =H21*I19 -> 1522.842 | J20: =I21*J19 -> 1644.9485 | ... L20: =K21*L19 -> 1919.3194
A21: 지배주주지분 | B21: =$F$8 -> 11956 | C21: =B21+C20 -> 12914.672 | D21: =C21+D20 -> 13950.213 | E21: =D21+E20 -> 15068.788 | F21: =E21+F20 -> 16277.054 | G21: =F21+G20 -> 17582.202 | H21: =G21+H20 -> 18992.002 | I21: =H21+I20 -> 20514.844 | J21: =I21+J20 -> 22159.792 | ... L21: =K21+L20 -> 25855.958
A22: 초과이익 | C22: =C20-B21*C17 -> -268.01367 | D22: =D20-C21*D17 -> -289.5039 | E22: =E20-D21*E17 -> -312.71728 | F22: =F20-E21*F17 -> -337.792 | G22: =G20-F21*G17 -> -364.87729 | H22: =H20-G21*H17 -> -394.13436 | I22: =I20-H21*I17 -> -425.73737 | J22: =J20-I21*J17 -> -459.87441 | ... L22: =L20-K21*L17 -> -536.57964
A23: PV of RI | B23: =NPV($B$3,C22:L22) -> -2219.996
B24: 분석시점 기준 | C24: 현재 기준
A25: RIM 주주가치 | B25: =B21+B23 -> 9736.004 | C25: =B25/(1+$B$3)^($H$8/365) -> 10964.267
A26: RIM 적정주가 | B26: =B25*100000000/($B$4-$B$5) -> 44214.128 | C26: =B26/(1+$B$3)^($H$8/365) -> 49792.041
A28: 초과이익 지속계수 | B28: 0.9
A29: 시점 | B29: =$F$7 -> 45657 | C29: =B29+365 -> 46022 | D29: =C29+365 -> 46387 | E29: =D29+365 -> 46752 | F29: =E29+365 -> 47117 | G29: =F29+365 -> 47482 | H29: =G29+365 -> 47847 | I29: =H29+365 -> 48212 | J29: =I29+365 -> 48577 | ... L29: =K29+365 -> 49307
A30: 요구수익률 | B30: =$B$3 -> 0.1026 | C30: =B30 -> 0.1026 | D30: =C30 -> 0.1026 | E30: =D30 -> 0.1026 | F30: =E30 -> 0.1026 | G30: =F30 -> 0.1026 | H30: =G30 -> 0.1026 | I30: =H30 -> 0.1026 | J30: =I30 -> 0.1026 | ... L30: =K30 -> 0.1026
A31: 초과이익률 | B31: =$B$7-B30 -> -0.022416667 | C31: =IF(YEAR(C16)>$J$7,0,B31*$B$28) -> -0.020175 | D31: =IF(YEAR(D16)>$J$7,0,C31*$B$28) -> -0.0181575 | E31: =IF(YEAR(E16)>$J$7,0,D31*$B$28) -> -0.01634175 | F31: =IF(YEAR(F16)>$J$7,0,E31*$B$28) -> -0.014707575 | G31: =IF(YEAR(G16)>$J$7,0,F31*$B$28) -> -0.013236818 | H31: =IF(YEAR(H16)>$J$7,0,G31*$B$28) -> -0.011913136 | I31: =IF(YEAR(I16)>$J$7,0,H31*$B$28) -> -0.010721822 | J31: =IF(YEAR(J16)>$J$7,0,I31*$B$28) -> -0.00964964 | ... L31: =IF(YEAR(L16)>$J$7,0,K31*$B$28) -> -0.0078162084
A32: ROE | B32: =B30+B31 -> 0.080183333 | C32: =C30+C31 -> 0.082425 | D32: =D30+D31 -> 0.0844425 | E32: =E30+E31 -> 0.08625825 | F32: =F30+F31 -> 0.087892425 | G32: =G30+G31 -> 0.089363182 | H32: =H30+H31 -> 0.090686864 | I32: =I30+I31 -> 0.091878178 | ... L32: =L30+L31 -> 0.094783792
A33: 지배주주순이익 | C33: =B34*C32 -> 985.4733 | D33: =C34*D32 -> 1092.8104 | E33: =D34*E32 -> 1210.5727 | F33: =E34*F32 -> 1339.9074 | G33: =F34*G32 -> 1482.0673 | H33: =G34*H32 -> 1638.4243 | I33: =H34*I32 -> 1810.483 | J33: =I34*J32 -> 1999.8956 | ... L33: =K34*L32 -> 2438.2289
A34: 지배주주지분 | B34: =$F$8 -> 11956 | C34: =B34+C33 -> 12941.473 | D34: =C34+D33 -> 14034.284 | E34: =D34+E33 -> 15244.856 | F34: =E34+F33 -> 16584.764 | G34: =F34+G33 -> 18066.831 | H34: =G34+H33 -> 19705.255 | I34: =H34+I33 -> 21515.738 | J34: =I34+J33 -> 23515.634 | ... L34: =K34+L33 -> 28162.341
A35: 초과이익 | C35: =C33-B34*C30 -> -241.2123 | D35: =D33-C34*D30 -> -234.9848 | E35: =E33-D34*E30 -> -229.34475 | F35: =F33-E34*F30 -> -224.21487 | G35: =G33-F34*G30 -> -219.52949 | H35: =H33-G34*H30 -> -215.23261 | I35: =I33-H34*I30 -> -211.27624 | J35: =J33-I34*J30 -> -207.61913 | ... L35: =L33-K34*L30 -> -201.06502
A36: PV of RI | B36: =NPV($B$3,C35:L35) -> -1351.5323
B37: 분석시점 기준 | C37: 현재 기준
A38: RIM 주주가치 | B38: =B34+B36 -> 10604.468 | C38: =B38/(1+$B$3)^($H$8/365) -> 11942.294
A39: RIM 적정주가 | B39: =B38*100000000/($B$4-$B$5) -> 48158.083 | C39: =B39/(1+$B$3)^($H$8/365) -> 54233.553
A41: 초과이익 지속계수 | B41: 0.8
A42: 시점 | B42: =$F$7 -> 45657 | C42: =B42+365 -> 46022 | D42: =C42+365 -> 46387 | E42: =D42+365 -> 46752 | F42: =E42+365 -> 47117 | G42: =F42+365 -> 47482 | H42: =G42+365 -> 47847 | I42: =H42+365 -> 48212 | J42: =I42+365 -> 48577 | ... L42: =K42+365 -> 49307
A43: 요구수익률 | B43: =$B$3 -> 0.1026 | C43: =B43 -> 0.1026 | D43: =C43 -> 0.1026 | E43: =D43 -> 0.1026 | F43: =E43 -> 0.1026 | G43: =F43 -> 0.1026 | H43: =G43 -> 0.1026 | I43: =H43 -> 0.1026 | J43: =I43 -> 0.1026 | ... L43: =K43 -> 0.1026
A44: 초과이익률 | B44: =$B$7-B43 -> -0.022416667 | C44: =IF(YEAR(C16)>$J$7,0,B44*$B$41) -> -0.017933333 | D44: =IF(YEAR(D16)>$J$7,0,C44*$B$41) -> -0.014346667 | E44: =IF(YEAR(E16)>$J$7,0,D44*$B$41) -> -0.011477333 | F44: =IF(YEAR(F16)>$J$7,0,E44*$B$41) -> -0.0091818667 | G44: =IF(YEAR(G16)>$J$7,0,F44*$B$41) -> -0.0073454933 | H44: =IF(YEAR(H16)>$J$7,0,G44*$B$41) -> -0.0058763947 | I44: =IF(YEAR(I16)>$J$7,0,H44*$B$41) -> -0.0047011157 | J44: =IF(YEAR(J16)>$J$7,0,I44*$B$41) -> -0.0037608926 | ... L44: =IF(YEAR(L16)>$J$7,0,K44*$B$41) -> -0.0024069713
A45: ROE | B45: =B43+B44 -> 0.080183333 | C45: =C43+C44 -> 0.084666667 | D45: =D43+D44 -> 0.088253333 | E45: =E43+E44 -> 0.091122667 | F45: =F43+F44 -> 0.093418133 | G45: =G43+G44 -> 0.095254507 | H45: =H43+H44 -> 0.096723605 | I45: =I43+I44 -> 0.097898884 | ... L45: =L43+L44 -> 0.10019303
A46: 지배주주순이익 | C46: =B47*C45 -> 1012.2747 | D46: =C47*D45 -> 1144.4935 | E46: =D47*E45 -> 1285.9931 | F46: =E47*F45 -> 1438.5235 | G46: =F47*G45 -> 1603.8273 | H46: =G47*H45 -> 1783.6908 | I46: =H47*I45 -> 1979.9856 | J46: =I47*J45 -> 2194.7015 | ... L46: =K47*L45 -> 2688.1255
A47: 지배주주지분 | B47: =$F$8 -> 11956 | C47: =B47+C46 -> 12968.275 | D47: =C47+D46 -> 14112.768 | E47: =D47+E46 -> 15398.761 | F47: =E47+F46 -> 16837.285 | G47: =F47+G46 -> 18441.112 | H47: =G47+H46 -> 20224.803 | I47: =H47+I46 -> 22204.788 | J47: =I47+J46 -> 24399.49 | ... L47: =K47+L46 -> 29517.592
A48: 초과이익 | C48: =C46-B47*C43 -> -214.41093 | D48: =D46-C47*D43 -> -186.05151 | E48: =E46-D47*E43 -> -161.97694 | F48: =F46-E47*F43 -> -141.38937 | G48: =G46-F47*G43 -> -123.67816 | H48: =H46-G47*H43 -> -108.36725 | I48: =I46-H47*I43 -> -95.079139 | J48: =J46-I47*J43 -> -83.509824 | ... L48: =L46-K47*L43 -> -64.577755
A49: PV of RI | B49: =NPV($B$3,C48:L48) -> -841.21557
B50: 분석시점 기준 | C50: 현재 기준
A51: RIM 주주가치 | B51: =B47+B49 -> 11114.784 | C51: =B51/(1+$B$3)^($H$8/365) -> 12516.99
A52: RIM 적정주가 | B52: =B51*100000000/($B$4-$B$5) -> 50475.585 | C52: =B52/(1+$B$3)^($H$8/365) -> 56843.424
B54: 1 | C54: 2 | D54: 3 | E54: 4 | F54: 5 | G54: =IF($F$7>G55-1,F54+1,"") | H54: =IF($F$7>H55-1,G54+1,"") | I54: =IF($F$7>I55-1,H54+1,"") | J54: =MAX(B54:I54)+1 -> 6 | K54: =J54+1 -> 7 | L54: =K54+1 -> 8 | M54: =L54+1 -> 9 | N54: =M54+1 -> 10 | O54: =N54+1 -> 11 | P54: =O54+1 -> 12 | Q54: =P54+1 -> 13 | R54: =Q54+1 -> 14 | S54: =R54+1 -> 15
B55: =E4 -> 44196 | C55: =F4 -> 44561 | D55: =G4 -> 44926 | E55: =H4 -> 45291 | F55: =I4 -> 45657 | G55: =J4 -> 46022 | H55: =K4 -> 46387 | I55: =L4 -> 46752 | J55: =C16 -> 46022 | K55: =D16 -> 46387 | L55: =E16 -> 46752 | M55: =F16 -> 47117 | N55: =G16 -> 47482 | O55: =H16 -> 47847 | P55: =I16 -> 48212 | Q55: =J16 -> 48577 | ... S55: =L16 -> 49307
A56: 초과이익 지속 | B56: =E5 -> 325 | C56: =F5 -> 524 | D56: =G5 -> 1054 | E56: =H5 -> 698 | F56: =I5 -> 855 | G56: =J5 -> 0 | H56: =K5 -> 0 | I56: =L5 -> 0 | J56: =C20 -> 958.67193 | K56: =D20 -> 1035.5414 | L56: =E20 -> 1118.5746 | M56: =F20 -> 1208.2657 | N56: =G20 -> 1305.1484 | O56: =H20 -> 1409.7996 | P56: =I20 -> 1522.842 | Q56: =J20 -> 1644.9485 | ... S56: =L20 -> 1919.3194
A57: 10년 감소 | B57: =E5 -> 325 | C57: =F5 -> 524 | D57: =G5 -> 1054 | E57: =H5 -> 698 | F57: =I5 -> 855 | G57: =J5 -> 0 | H57: =K5 -> 0 | I57: =L5 -> 0 | J57: =C33 -> 985.4733 | K57: =D33 -> 1092.8104 | L57: =E33 -> 1210.5727 | M57: =F33 -> 1339.9074 | N57: =G33 -> 1482.0673 | O57: =H33 -> 1638.4243 | P57: =I33 -> 1810.483 | Q57: =J33 -> 1999.8956 | ... S57: =L33 -> 2438.2289
A58: 5년 감소 | B58: =E5 -> 325 | C58: =F5 -> 524 | D58: =G5 -> 1054 | E58: =H5 -> 698 | F58: =I5 -> 855 | G58: =J5 -> 0 | H58: =K5 -> 0 | I58: =L5 -> 0 | J58: =C46 -> 1012.2747 | K58: =D46 -> 1144.4935 | L58: =E46 -> 1285.9931 | M58: =F46 -> 1438.5235 | N58: =G46 -> 1603.8273 | O58: =H46 -> 1783.6908 | P58: =I46 -> 1979.9856 | Q58: =J46 -> 2194.7015 | ... S58: =L46 -> 2688.1255
B60: 1 | C60: 2 | D60: 3 | E60: 4 | F60: 5 | G60: 6 | H60: 7 | I60: 8 | J60: 9 | K60: 10 | L60: 11 | M60: 12 | N60: 13 | O60: 14 | P60: 15
B61: =HLOOKUP(B$60,$B$54:$S$58,2,FALSE) -> 44196 | C61: =HLOOKUP(C$60,$B$54:$S$58,2,FALSE) -> 44561 | D61: =HLOOKUP(D$60,$B$54:$S$58,2,FALSE) -> 44926 | E61: =HLOOKUP(E$60,$B$54:$S$58,2,FALSE) -> 45291 | F61: =HLOOKUP(F$60,$B$54:$S$58,2,FALSE) -> 45657 | G61: =HLOOKUP(G$60,$B$54:$S$58,2,FALSE) -> 46022 | H61: =HLOOKUP(H$60,$B$54:$S$58,2,FALSE) -> 46387 | I61: =HLOOKUP(I$60,$B$54:$S$58,2,FALSE) -> 46752 | ... P61: =HLOOKUP(P$60,$B$54:$S$58,2,FALSE) -> 49307
A62: 초과이익 지속 | B62: =HLOOKUP(B$60,$B$54:$S$58,3,FALSE) -> 325 | C62: =HLOOKUP(C$60,$B$54:$S$58,3,FALSE) -> 524 | D62: =HLOOKUP(D$60,$B$54:$S$58,3,FALSE) -> 1054 | E62: =HLOOKUP(E$60,$B$54:$S$58,3,FALSE) -> 698 | F62: =HLOOKUP(F$60,$B$54:$S$58,3,FALSE) -> 855 | G62: =HLOOKUP(G$60,$B$54:$S$58,3,FALSE) -> 958.67193 | H62: =HLOOKUP(H$60,$B$54:$S$58,3,FALSE) -> 1035.5414 | I62: =HLOOKUP(I$60,$B$54:$S$58,3,FALSE) -> 1118.5746 | ... P62: =HLOOKUP(P$60,$B$54:$S$58,3,FALSE) -> 1919.3194
A63: 10년 감소 | B63: =HLOOKUP(B$60,$B$54:$S$58,4,FALSE) -> 325 | C63: =HLOOKUP(C$60,$B$54:$S$58,4,FALSE) -> 524 | D63: =HLOOKUP(D$60,$B$54:$S$58,4,FALSE) -> 1054 | E63: =HLOOKUP(E$60,$B$54:$S$58,4,FALSE) -> 698 | F63: =HLOOKUP(F$60,$B$54:$S$58,4,FALSE) -> 855 | G63: =HLOOKUP(G$60,$B$54:$S$58,4,FALSE) -> 985.4733 | H63: =HLOOKUP(H$60,$B$54:$S$58,4,FALSE) -> 1092.8104 | I63: =HLOOKUP(I$60,$B$54:$S$58,4,FALSE) -> 1210.5727 | ... P63: =HLOOKUP(P$60,$B$54:$S$58,4,FALSE) -> 2438.2289
A64: 5년 감소 | B64: =HLOOKUP(B$60,$B$54:$S$58,5,FALSE) -> 325 | C64: =HLOOKUP(C$60,$B$54:$S$58,5,FALSE) -> 524 | D64: =HLOOKUP(D$60,$B$54:$S$58,5,FALSE) -> 1054 | E64: =HLOOKUP(E$60,$B$54:$S$58,5,FALSE) -> 698 | F64: =HLOOKUP(F$60,$B$54:$S$58,5,FALSE) -> 855 | G64: =HLOOKUP(G$60,$B$54:$S$58,5,FALSE) -> 1012.2747 | H64: =HLOOKUP(H$60,$B$54:$S$58,5,FALSE) -> 1144.4935 | I64: =HLOOKUP(I$60,$B$54:$S$58,5,FALSE) -> 1285.9931 | ... P64: =HLOOKUP(P$60,$B$54:$S$58,5,FALSE) -> 2688.1255

Sheet RIM수기계산
A1: 주황색 셀만 입력하거나 선택합니다.
A3: [Type 1] 단순입력(간편식-책)
A5: 자기자본 | B5: 1513
A6: 예상 ROE | B6: 0.1522
A7: 요구수익률(할인률) | B7: 0.0805
A8: 기업가치 | B8: =B5+(B5*(B6-B7))/B7 -> 2860.6037
A10: 주식수 | B10: 15179843
A11: 적정주가 | B11: =B8*100000000/B10 -> 18844.752
A13: 초과이익 가정 | B13: 적정주주가치 | C13: 적정주가 | D13: 판단 | F13: 초과이익 | G13: =B5*(B6-B7) -> 108.4821
A14: 지속 | B14: =B8 -> 2860.6037 | C14: =B11 -> 18844.752 | D14: 매도가격 | F14: 지속계수
A15: 10%씩 감소 | B15: =B5+G13*F15/(1+B7-F15) -> 2053.908 | C15: =B15*100000000/B10 -> 13530.496 | D15: 적정가격 | F15: 0.9
A16: 20%씩 감소 | B16: =B5+G13*F16/(1+B7-F16) -> 1822.3964 | C16: =B16*100000000/B10 -> 12005.37 | D16: 매수가격 | F16: 0.8
A18: [Type 2] 단순입력(성장반영 10년 시뮬레이션)
A20: 초과이익 가정 | B20: 적정주주가치 | C20: 적정주가 | D20: 판단
A21: 지속 | B21: =B34 -> 2876.5367 | C21: =B35 -> 18949.713 | D21: 매도가격
A22: 10%씩 감소 | B22: =B46 -> 2214.6094 | C22: =B47 -> 14589.146 | D22: 적정가격
A23: 20%씩 감소 | B23: =B58 -> 1910.2924 | C23: =B59 -> 12584.401 | D23: 매수가격
A25: 초과이익 지속계수 | B25: 1
A26: 시점 | B26: Y-0 | C26: Y-1 | D26: Y-2 | E26: Y-3 | F26: Y-4 | G26: Y-5 | H26: Y-6 | I26: Y-7 | J26: Y-8 | K26: Y-9 | L26: Y-10
A27: 요구수익률 | B27: =$B$7 -> 0.0805 | C27: =B27 -> 0.0805 | D27: =C27 -> 0.0805 | E27: =D27 -> 0.0805 | F27: =E27 -> 0.0805 | G27: =F27 -> 0.0805 | H27: =G27 -> 0.0805 | I27: =H27 -> 0.0805 | J27: =I27 -> 0.0805 | ... L27: =K27 -> 0.0805
A28: 초과이익률 | B28: =$B$6-B27 -> 0.0717 | C28: =B28*$B$25 -> 0.0717 | D28: =C28*$B$25 -> 0.0717 | E28: =D28*$B$25 -> 0.0717 | F28: =E28*$B$25 -> 0.0717 | G28: =F28*$B$25 -> 0.0717 | H28: =G28*$B$25 -> 0.0717 | I28: =H28*$B$25 -> 0.0717 | J28: =I28*$B$25 -> 0.0717 | ... L28: =K28*$B$25 -> 0.0717
A29: ROE | B29: =B27+B28 -> 0.1522 | C29: =C27+C28 -> 0.1522 | D29: =D27+D28 -> 0.1522 | E29: =E27+E28 -> 0.1522 | F29: =F27+F28 -> 0.1522 | G29: =G27+G28 -> 0.1522 | H29: =H27+H28 -> 0.1522 | I29: =I27+I28 -> 0.1522 | ... L29: =L27+L28 -> 0.1522
A30: 지배주주순이익 | C30: =B31*C29 -> 230.2786 | D30: =C31*D29 -> 265.327 | E30: =D31*E29 -> 305.70977 | F30: =E31*F29 -> 352.2388 | G30: =F31*G29 -> 405.84955 | H30: =G31*H29 -> 467.61985 | I30: =H31*I29 -> 538.79159 | J30: =I31*J29 -> 620.79567 | ... L30: =K31*L29 -> 824.1465
A31: 지배주주지분 | B31: =$B$5 -> 1513 | C31: =B31+C30 -> 1743.2786 | D31: =C31+D30 -> 2008.6056 | E31: =D31+E30 -> 2314.3154 | F31: =E31+F30 -> 2666.5542 | G31: =F31+G30 -> 3072.4037 | H31: =G31+H30 -> 3540.0236 | I31: =H31+I30 -> 4078.8152 | J31: =I31+J30 -> 4699.6108 | ... L31: =K31+L30 -> 6239.0381
A32: 초과이익 | C32: =C30-B31*C27 -> 108.4821 | D32: =D30-C31*D27 -> 124.99308 | E32: =E30-D31*E27 -> 144.01702 | F32: =F30-E31*F27 -> 165.93641 | G32: =G30-F31*G27 -> 191.19193 | H32: =H30-G31*H27 -> 220.29135 | I32: =I30-H31*I27 -> 253.81969 | J32: =J30-I31*J27 -> 292.45105 | ... L32: =L30-K31*L27 -> 388.24773
A33: PV of RI | B33: =NPV($B$7,C32:L32) -> 1363.5367
A34: RIM 주주가치 | B34: =B31+B33 -> 2876.5367
A35: RIM 적정주가 | B35: =B34*100000000/$B$10 -> 18949.713
A37: 초과이익 지속계수 | B37: 0.9
A38: 시점 | B38: Y-0 | C38: Y-1 | D38: Y-2 | E38: Y-3 | F38: Y-4 | G38: Y-5 | H38: Y-6 | I38: Y-7 | J38: Y-8 | K38: Y-9 | L38: Y-10
A39: 요구수익률 | B39: =$B$7 -> 0.0805 | C39: =B39 -> 0.0805 | D39: =C39 -> 0.0805 | E39: =D39 -> 0.0805 | F39: =E39 -> 0.0805 | G39: =F39 -> 0.0805 | H39: =G39 -> 0.0805 | I39: =H39 -> 0.0805 | J39: =I39 -> 0.0805 | ... L39: =K39 -> 0.0805
A40: 초과이익률 | B40: =$B$6-B39 -> 0.0717 | C40: =B40*$B$37 -> 0.06453 | D40: =C40*$B$37 -> 0.058077 | E40: =D40*$B$37 -> 0.0522693 | F40: =E40*$B$37 -> 0.04704237 | G40: =F40*$B$37 -> 0.042338133 | H40: =G40*$B$37 -> 0.03810432 | I40: =H40*$B$37 -> 0.034293888 | J40: =I40*$B$37 -> 0.030864499 | ... L40: =K40*$B$37 -> 0.025000244
A41: ROE | B41: =B39+B40 -> 0.1522 | C41: =C39+C40 -> 0.14503 | D41: =D39+D40 -> 0.138577 | E41: =E39+E40 -> 0.1327693 | F41: =F39+F40 -> 0.12754237 | G41: =G39+G40 -> 0.12283813 | H41: =H39+H40 -> 0.11860432 | I41: =I39+I40 -> 0.11479389 | ... L41: =L39+L40 -> 0.10550024
A42: 지배주주순이익 | C42: =B43*C41 -> 219.43039 | D42: =C43*D41 -> 240.07501 | E42: =D43*E41 -> 261.88816 | F42: =E43*F41 -> 284.97985 | G42: =F43*G41 -> 309.47513 | H42: =G43*H41 -> 335.51366 | I42: =H43*I41 -> 363.24944 | J42: =I43*J41 -> 392.8507 | ... L42: =K43*L41 -> 458.39459
A43: 지배주주지분 | B43: =$B$5 -> 1513 | C43: =B43+C42 -> 1732.4304 | D43: =C43+D42 -> 1972.5054 | E43: =D43+E42 -> 2234.3936 | F43: =E43+F42 -> 2519.3734 | G43: =F43+G42 -> 2828.8485 | H43: =G43+H42 -> 3164.3622 | I43: =H43+I42 -> 3527.6116 | J43: =I43+J42 -> 3920.4623 | ... L43: =K43+L42 -> 4803.3569
A44: 초과이익 | C44: =C42-B43*C39 -> 97.63389 | D44: =D42-C43*D39 -> 100.61436 | E44: =E42-D43*E39 -> 103.10148 | F44: =F42-E43*F39 -> 105.11117 | G44: =G42-F43*G39 -> 106.66557 | H44: =H42-G43*H39 -> 107.79135 | I44: =I42-H43*I39 -> 108.51828 | J44: =J42-I43*J39 -> 108.87797 | ... L44: =L42-K43*L39 -> 108.62512
A45: PV of RI | B45: =NPV($B$7,C44:L44) -> 701.60944
A46: RIM 주주가치 | B46: =B43+B45 -> 2214.6094
A47: RIM 적정주가 | B47: =B46*100000000/$B$10 -> 14589.146
A49: 초과이익 지속계수 | B49: 0.8
A50: 시점 | B50: Y-0 | C50: Y-1 | D50: Y-2 | E50: Y-3 | F50: Y-4 | G50: Y-5 | H50: Y-6 | I50: Y-7 | J50: Y-8 | K50: Y-9 | L50: Y-10
A51: 요구수익률 | B51: =$B$7 -> 0.0805 | C51: =B51 -> 0.0805 | D51: =C51 -> 0.0805 | E51: =D51 -> 0.0805 | F51: =E51 -> 0.0805 | G51: =F51 -> 0.0805 | H51: =G51 -> 0.0805 | I51: =H51 -> 0.0805 | J51: =I51 -> 0.0805 | ... L51: =K51 -> 0.0805
A52: 초과이익률 | B52: =$B$6-B51 -> 0.0717 | C52: =B52*$B$49 -> 0.05736 | D52: =C52*$B$49 -> 0.045888 | E52: =D52*$B$49 -> 0.0367104 | F52: =E52*$B$49 -> 0.02936832 | G52: =F52*$B$49 -> 0.023494656 | H52: =G52*$B$49 -> 0.018795725 | I52: =H52*$B$49 -> 0.01503658 | J52: =I52*$B$49 -> 0.012029264 | ... L52: =K52*$B$49 -> 0.0076987289
A53: ROE | B53: =B51+B52 -> 0.1522 | C53: =C51+C52 -> 0.13786 | D53: =D51+D52 -> 0.126388 | E53: =E51+E52 -> 0.1172104 | F53: =F51+F52 -> 0.10986832 | G53: =G51+G52 -> 0.10399466 | H53: =H51+H52 -> 0.099295725 | I53: =I51+I52 -> 0.09553658 | ... L53: =L51+L52 -> 0.088198729
A54: 지배주주순이익 | C54: =B55*C53 -> 208.58218 | D54: =C55*D53 -> 217.58733 | E54: =D55*E53 -> 227.29083 | F54: =E55*F53 -> 238.02536 | G54: =F55*G53 -> 250.05366 | H54: =G55*H53 -> 263.58441 | I54: =H55*I53 -> 278.78756 | J54: =I55*J53 -> 295.80785 | ... L54: =K55*L53 -> 335.81622
A55: 지배주주지분 | B55: =$B$5 -> 1513 | C55: =B55+C54 -> 1721.5822 | D55: =C55+D54 -> 1939.1695 | E55: =D55+E54 -> 2166.4603 | F55: =E55+F54 -> 2404.4857 | G55: =F55+G54 -> 2654.5394 | H55: =G55+H54 -> 2918.1238 | I55: =H55+I54 -> 3196.9113 | J55: =I55+J54 -> 3492.7192 | ... L55: =K55+L54 -> 4143.3112
A56: 초과이익 | C56: =C54-B55*C51 -> 86.78568 | D56: =D54-C55*D51 -> 78.999963 | E56: =E54-D55*E51 -> 71.187688 | F56: =F54-E55*F51 -> 63.625301 | G56: =G54-F55*G51 -> 56.492564 | H56: =H54-G55*H51 -> 49.893991 | I56: =I54-H55*I51 -> 43.878601 | J56: =J54-I55*J51 -> 38.45649 | ... L56: =L54-K55*L51 -> 29.312871
A57: PV of RI | B57: =NPV($B$7,C56:L56) -> 397.29236
A58: RIM 주주가치 | B58: =B55+B57 -> 1910.2924
A59: RIM 적정주가 | B59: =B58*100000000/$B$10 -> 12584.401
A61: [Type 3] 상세입력(성장반영 10년 시뮬레이션)
A62: 주황색 셀만 입력하거나 선택합니다.
A64: 최근 결산연도 | B64: 2019
A65: 요구수익률 | B65: 0.0805
A66: 발행주식수(보통+우선) | B66: =482432493+17482000 -> 499914493
A67: 자기주식 | B67: 2603926
B69: Y-2 | C69: Y-1 | D69: Y
B70: =C70-1 -> 2017 | C70: =D70-1 -> 2018 | D70: =B64 -> 2019 | E70: 과거 ROE 추세 | F70: 단순추정 ROE | K70: 1순위 | L70: =IF(L71="컨센없음",F71,L71) -> 0.072630407
A71: 과거 ROE(직접입력) | B71: 0.0913 | C71: 0.0921 | D71: 0.0909 | E71: =IF(D71>C71,IF(C71>B71,"상승추세","추세없음"),IF(C71<B71,"하락추세","추세없음")) -> 추세없음 | F71: =IF(E71="상승추세",D71,IF(E71="하락추세",D71,(D71*3+C71*2+B71)/6)) -> 0.091366667 | K71: 컨센서스 | L71: =IF(E76="",IF(D76="",IF(C76="","컨센없음",C76),D76),E76) -> 0.072630407
B72: =B76 -> 0.0909 | C72: =C76 -> 0.076663888 | D72: =D76 -> 0.073659114 | E72: =E76 -> 0.072630407 | K72: 가중평균 | L72: =(D71*3+C71*2+B71)/6 -> 0.091366667
A73: 컨센 ROE(있는 자료만) | B73: =D70&"(확정)" -> 2019(확정) | C73: =D70+1&"(예상)" -> 2020(예상) | D73: =D70+2&"(예상)" -> 2021(예상) | E73: =D70+3&"(예상)" -> 2022(예상) | G73: =D70+G74 -> 2022 | K73: 최근 | L73: =D71 -> 0.0909
A74: 지배주주순이익(입력) | B74: 34035 | C74: 31080 | D74: 31853 | E74: 33305 | G74: =COUNT(C74:E74) -> 3 | K74: 별도 추정 | L74: =B79 -> 0.15
A75: 지배주주지분(입력) | B75: 391779 | C75: 419033 | D75: 445843 | E75: 471266 | G75: =COUNT(C75:E75) -> 3
A76: 컨센 ROE(계산) | B76: =D71 -> 0.0909 | C76: =IF(C74*C75=0,"",C74*2/(B75+C75)) -> 0.076663888 | D76: =IF(D74*D75=0,"",D74*2/(C75+D75)) -> 0.073659114 | E76: =IF(E74*E75=0,"",E74*2/(D75+E75)) -> 0.072630407 | G76: =MIN(G74:G75) -> 3
B77: =DATE(D70,12,31) -> 43830 | C77: =DATE(D70+1,12,31) -> 44196 | D77: =DATE(D70+2,12,31) -> 44561 | E77: =DATE(D70+3,12,31) -> 44926
A78: ROE 추정 | B78: 1순위 | C78: =VLOOKUP($B$78,$K$70:$L$74,2,FALSE) -> 0.072630407 | E78: 분석기준시점 | F78: =HLOOKUP(F79,$B$75:$E$77,3,FALSE) -> 44926 | G78: 현재 | H78: =TODAY() -> 46101
A79: =IF(B78="별도 추정","별도 추정 ROE(옵션)","") | B79: 0.15 | E79: 기준시점 주주지분 | F79: =IF(ISNA(HLOOKUP(C78,B72:E75,4,FALSE)),B75,HLOOKUP(C78,B72:E75,4,FALSE)) -> 471266 | G79: 기준시점-현재 | H79: =F78-H78 -> -1175
A81: 초과이익 가정 | B81: 적정주주가치 | C81: 적정주가 | D81: 판단
A82: 지속 | B82: =C96 -> 562035.26 | C82: =C97 -> 113014.94 | D82: 매도가격
A83: 10%씩 감소 | B83: =C109 -> 481615.32 | C83: =C110 -> 96843.974 | D83: 적정가격
A84: 20%씩 감소 | B84: =C122 -> 489746.28 | C84: =C123 -> 98478.962 | D84: 매수가격
A86: 초과이익 지속계수 | B86: 1
A87: 시점 | B87: Y-0 | C87: Y-1 | D87: Y-2 | E87: Y-3 | F87: Y-4 | G87: Y-5 | H87: Y-6 | I87: Y-7 | J87: Y-8 | K87: Y-9 | L87: Y-10
A88: 요구수익률 | B88: =$B$65 -> 0.0805 | C88: =B88 -> 0.0805 | D88: =C88 -> 0.0805 | E88: =D88 -> 0.0805 | F88: =E88 -> 0.0805 | G88: =F88 -> 0.0805 | H88: =G88 -> 0.0805 | I88: =H88 -> 0.0805 | J88: =I88 -> 0.0805 | ... L88: =K88 -> 0.0805
A89: 초과이익률 | B89: =$C$78-B88 -> -0.0078695929 | C89: =B89*$B$86 -> -0.0078695929 | D89: =C89*$B$86 -> -0.0078695929 | E89: =D89*$B$86 -> -0.0078695929 | F89: =E89*$B$86 -> -0.0078695929 | G89: =F89*$B$86 -> -0.0078695929 | H89: =G89*$B$86 -> -0.0078695929 | I89: =H89*$B$86 -> -0.0078695929 | J89: =I89*$B$86 -> -0.0078695929 | ... L89: =K89*$B$86 -> -0.0078695929
A90: ROE | B90: =B88+B89 -> 0.072630407 | C90: =C88+C89 -> 0.072630407 | D90: =D88+D89 -> 0.072630407 | E90: =E88+E89 -> 0.072630407 | F90: =F88+F89 -> 0.072630407 | G90: =G88+G89 -> 0.072630407 | H90: =H88+H89 -> 0.072630407 | I90: =I88+I89 -> 0.072630407 | ... L90: =L88+L89 -> 0.072630407
A91: 지배주주순이익 | C91: =B92*C90 -> 34228.241 | D91: =C92*D90 -> 36714.253 | E91: =D92*E90 -> 39380.824 | F91: =E92*F90 -> 42241.069 | G91: =F92*G90 -> 45309.055 | H91: =G92*H90 -> 48599.87 | I91: =H92*I90 -> 52129.698 | J91: =I92*J90 -> 55915.9 | ... L91: =K92*L90 -> 64333.255
A92: 지배주주지분 | B92: =$F$79 -> 471266 | C92: =B92+C91 -> 505494.24 | D92: =C92+D91 -> 542208.49 | E92: =D92+E91 -> 581589.32 | F92: =E92+F91 -> 623830.39 | G92: =F92+G91 -> 669139.44 | H92: =G92+H91 -> 717739.31 | I92: =H92+I91 -> 769869.01 | J92: =I92+J91 -> 825784.91 | ... L92: =K92+L91 -> 950095.26
A93: 초과이익 | C93: =C91-B92*C88 -> -3708.6716 | D93: =D91-C92*D88 -> -3978.0339 | E93: =E91-D92*E88 -> -4266.9601 | F93: =F91-E92*F88 -> -4576.8712 | G93: =G91-F92*G88 -> -4909.2912 | H93: =H91-G92*H88 -> -5265.855 | I93: =I91-H92*I88 -> -5648.3162 | J93: =J91-I92*J88 -> -6058.5557 | ... L93: =L91-K92*L88 -> -6970.5864
A94: PV of RI | B94: =NPV($B$7,C93:L93) -> -33220.283
B95: 분석시점 기준 | C95: 현재 기준
A96: RIM 주주가치 | B96: =B92+B94 -> 438045.72 | C96: =B96/(1+$B$65)^($H$79/365) -> 562035.26
A97: RIM 적정주가 | B97: =B96*100000000/($B$66-$B$67) -> 88082.93 | C97: =B97/(1+$B$65)^($H$79/365) -> 113014.94
A99: 초과이익 지속계수 | B99: 0.9
A100: 시점 | B100: Y-0 | C100: Y-1 | D100: Y-2 | E100: Y-3 | F100: Y-4 | G100: Y-5 | H100: Y-6 | I100: Y-7 | J100: Y-8 | K100: Y-9 | L100: Y-10
A101: 요구수익률 | B101: =$B$65 -> 0.0805 | C101: =B101 -> 0.0805 | D101: =C101 -> 0.0805 | E101: =D101 -> 0.0805 | F101: =E101 -> 0.0805 | G101: =F101 -> 0.0805 | H101: =G101 -> 0.0805 | I101: =H101 -> 0.0805 | J101: =I101 -> 0.0805 | ... L101: =K101 -> 0.0805
A102: 초과이익률 | B102: =$C$78-B101 -> -0.0078695929 | C102: =B102*$B$99 -> -0.0070826336 | D102: =C102*$B$99 -> -0.0063743703 | E102: =D102*$B$99 -> -0.0057369332 | F102: =E102*$B$99 -> -0.0051632399 | G102: =F102*$B$99 -> -0.0046469159 | H102: =G102*$B$99 -> -0.0041822243 | I102: =H102*$B$99 -> -0.0037640019 | J102: =I102*$B$99 -> -0.0033876017 | ... L102: =K102*$B$99 -> -0.0027439574
A103: ROE | B103: =B101+B102 -> 0.072630407 | C103: =C101+C102 -> 0.073417366 | D103: =D101+D102 -> 0.07412563 | E103: =E101+E102 -> 0.074763067 | F103: =F101+F102 -> 0.07533676 | G103: =G101+G102 -> 0.075853084 | H103: =H101+H102 -> 0.076317776 | I103: =I101+I102 -> 0.076735998 | ... L103: =L101+L102 -> 0.077756043
A104: 지배주주순이익 | C104: =B105*C103 -> 28763.382 | D104: =C105*D103 -> 31172.969 | E104: =D105*E103 -> 33771.625 | F104: =E105*F103 -> 36575.016 | G104: =F105*G103 -> 39600.012 | H104: =G105*H103 -> 42864.795 | I104: =H105*I103 -> 46388.967 | J104: =I105*J103 -> 50193.676 | ... L104: =K105*L103 -> 58737.784
A105: 지배주주지분 | B105: =$B$75 -> 391779 | C105: =B105+C104 -> 420542.38 | D105: =C105+D104 -> 451715.35 | E105: =D105+E104 -> 485486.98 | F105: =E105+F104 -> 522061.99 | G105: =F105+G104 -> 561662 | H105: =G105+H104 -> 604526.8 | I105: =H105+I104 -> 650915.77 | J105: =I105+J104 -> 701109.44 | ... L105: =K105+L104 -> 814148.96
A106: 초과이익 | C106: =C104-B105*C101 -> -2774.8271 | D106: =D104-C105*D101 -> -2680.6929 | E106: =E104-D105*E101 -> -2591.4608 | F106: =F104-E105*F101 -> -2506.6857 | G106: =G104-F105*G101 -> -2425.9782 | H106: =H104-G105*H101 -> -2348.9965 | I106: =I104-H105*I101 -> -2275.44 | J106: =J104-I105*J101 -> -2205.0434 | ... L106: =L104-K105*L101 -> -2072.8161
A107: PV of RI | B107: =NPV($B$7,C106:L106) -> -16411.937
B108: 분석시점 기준 | C108: 현재 기준
A109: RIM 주주가치 | B109: =B105+B107 -> 375367.06 | C109: =B109/(1+$B$65)^($H$79/365) -> 481615.32
A110: RIM 적정주가 | B110: =B109*100000000/($B$66-$B$67) -> 75479.406 | C110: =B110/(1+$B$65)^($H$79/365) -> 96843.974
A112: 초과이익 지속계수 | B112: 0.8
A113: 시점 | B113: Y-0 | C113: Y-1 | D113: Y-2 | E113: Y-3 | F113: Y-4 | G113: Y-5 | H113: Y-6 | I113: Y-7 | J113: Y-8 | K113: Y-9 | L113: Y-10
A114: 요구수익률 | B114: =$B$65 -> 0.0805 | C114: =B114 -> 0.0805 | D114: =C114 -> 0.0805 | E114: =D114 -> 0.0805 | F114: =E114 -> 0.0805 | G114: =F114 -> 0.0805 | H114: =G114 -> 0.0805 | I114: =H114 -> 0.0805 | J114: =I114 -> 0.0805 | ... L114: =K114 -> 0.0805
A115: 초과이익률 | B115: =$C$78-B114 -> -0.0078695929 | C115: =B115*$B$112 -> -0.0062956743 | D115: =C115*$B$112 -> -0.0050365395 | E115: =D115*$B$112 -> -0.0040292316 | F115: =E115*$B$112 -> -0.0032233853 | G115: =F115*$B$112 -> -0.0025787082 | H115: =G115*$B$112 -> -0.0020629666 | I115: =H115*$B$112 -> -0.0016503733 | J115: =I115*$B$112 -> -0.0013202986 | ... L115: =K115*$B$112 -> -0.00084499111
A116: ROE | B116: =B114+B115 -> 0.072630407 | C116: =C114+C115 -> 0.074204326 | D116: =D114+D115 -> 0.075463461 | E116: =E114+E115 -> 0.076470768 | F116: =F114+F115 -> 0.077276615 | G116: =G114+G115 -> 0.077921292 | H116: =H114+H115 -> 0.078437033 | I116: =I114+I115 -> 0.078849627 | ... L116: =L114+L115 -> 0.079655009
...
